{"webpage_url_basename": "watch", "channel_url": "https://www.youtube.com/channel/UCW6JA9R8FtNXlwN0yZ_ILbQ", "uploader": "LEMAN PRODUCTIONS Ltd", "_filename": "4SqMWpCcP50.mp4", "formats": [{"width": null, "filesize": 11254835, "fps": null, "ext": "webm", "http_headers": {"Accept-Charset": "ISO-8859-1,utf-8;q=0.7,*;q=0.7", "User-Agent": "Mozilla/5.0 (Windows NT 10.0; Win64; x64) AppleWebKit/537.36 (KHTML, like Gecko) Chrome/74.0.3726.0 Safari/537.36", "Accept": "text/html,application/xhtml+xml,application/xml;q=0.9,*/*;q=0.8", "Accept-Encoding": "gzip, deflate", "Accept-Language": "en-us,en;q=0.5"}, "format_note": "tiny", "asr": 48000, "downloader_options": {"http_chunk_size": 10485760}, "container": "webm_dash", "acodec": "opus", "vcodec": "none", "url": "https://r1---sn-vuxbavcx-5uid.googlevideo.com/videoplayback?expire=1638297138&ei=0hmmYe31DZSBgQf71ZVA&ip=79.129.41.108&id=o-ABsktdzF-pG9E2NRbLDYQWPl2UIjCGgM4wlwCQlIaE1n&itag=249&source=youtube&requiressl=yes&mh=wI&mm=31%2C29&mn=sn-vuxbavcx-5uid%2Csn-4g5lzned&ms=au%2Crdu&mv=m&mvi=1&pl=20&initcwndbps=835000&vprv=1&mime=audio%2Fwebm&ns=HgS-gNV31uknf0hQClv_wCAG&gir=yes&clen=11254835&dur=1761.061&lmt=1620791804658613&mt=1638275337&fvip=1&keepalive=yes&fexp=24001373%2C24007246&beids=23886201&c=WEB&txp=5311222&n=iwfAPWQxtKCDFWIX&sparams=expire%2Cei%2Cip%2Cid%2Citag%2Csource%2Crequiressl%2Cvprv%2Cmime%2Cns%2Cgir%2Cclen%2Cdur%2Clmt&sig=AOq0QJ8wRgIhAME4MEmeXA8r0qKLdUM66HT6bXj9ryL2KvkVmxK9D5P7AiEAxnvdLJf3DgFRnwuUQsuM9wPd8cmxaaxk2XR57oLF1e0%3D&lsparams=mh%2Cmm%2Cmn%2Cms%2Cmv%2Cmvi%2Cpl%2Cinitcwndbps&lsig=AG3C_xAwRQIhAJ3YCRnjrJHRmXIhc2AAqhxUz4MVxCGdNS758yUcmlX_AiBsP9xwHEfl2NZ82syKirmjYxRSKaUzMYF2y9_LKXYkJg%3D%3D", "format": "249 - audio only (tiny)", "abr": 51.127, "tbr": 51.127, "quality": 0, "protocol": "https", "format_id": "249", "height": null}, {"width": null, "filesize": 13962248, "fps": null, "ext": "webm", "http_headers": {"Accept-Charset": "ISO-8859-1,utf-8;q=0.7,*;q=0.7", "User-Agent": "Mozilla/5.0 (Windows NT 10.0; Win64; x64) AppleWebKit/537.36 (KHTML, like Gecko) Chrome/74.0.3726.0 Safari/537.36", "Accept": "text/html,application/xhtml+xml,application/xml;q=0.9,*/*;q=0.8", "Accept-Encoding": "gzip, deflate", "Accept-Language": "en-us,en;q=0.5"}, "format_note": "tiny", "asr": 48000, "downloader_options": {"http_chunk_size": 10485760}, "container": "webm_dash", "acodec": "opus", "vcodec": "none", "url": "https://r1---sn-vuxbavcx-5uid.googlevideo.com/videoplayback?expire=1638297138&ei=0hmmYe31DZSBgQf71ZVA&ip=79.129.41.108&id=o-ABsktdzF-pG9E2NRbLDYQWPl2UIjCGgM4wlwCQlIaE1n&itag=250&source=youtube&requiressl=yes&mh=wI&mm=31%2C29&mn=sn-vuxbavcx-5uid%2Csn-4g5lzned&ms=au%2Crdu&mv=m&mvi=1&pl=20&initcwndbps=835000&vprv=1&mime=audio%2Fwebm&ns=HgS-gNV31uknf0hQClv_wCAG&gir=yes&clen=13962248&dur=1761.061&lmt=1620791823179880&mt=1638275337&fvip=1&keepalive=yes&fexp=24001373%2C24007246&beids=23886201&c=WEB&txp=5311222&n=iwfAPWQxtKCDFWIX&sparams=expire%2Cei%2Cip%2Cid%2Citag%2Csource%2Crequiressl%2Cvprv%2Cmime%2Cns%2Cgir%2Cclen%2Cdur%2Clmt&sig=AOq0QJ8wRQIgXP9y4WRZoYUAqGbnGzvv5WIS8HhkcMVK6RjD_pD7eMcCIQDD9PBnMsJ82l5Ko6JoUNvzvq8xjm7JUTW6Qjss7lOh3g%3D%3D&lsparams=mh%2Cmm%2Cmn%2Cms%2Cmv%2Cmvi%2Cpl%2Cinitcwndbps&lsig=AG3C_xAwRQIhAJ3YCRnjrJHRmXIhc2AAqhxUz4MVxCGdNS758yUcmlX_AiBsP9xwHEfl2NZ82syKirmjYxRSKaUzMYF2y9_LKXYkJg%3D%3D", "format": "250 - audio only (tiny)", "abr": 63.426, "tbr": 63.426, "quality": 0, "protocol": "https", "format_id": "250", "height": null}, {"width": null, "filesize": 28371181, "fps": null, "ext": "webm", "http_headers": {"Accept-Charset": "ISO-8859-1,utf-8;q=0.7,*;q=0.7", "User-Agent": "Mozilla/5.0 (Windows NT 10.0; Win64; x64) AppleWebKit/537.36 (KHTML, like Gecko) Chrome/74.0.3726.0 Safari/537.36", "Accept": "text/html,application/xhtml+xml,application/xml;q=0.9,*/*;q=0.8", "Accept-Encoding": "gzip, deflate", "Accept-Language": "en-us,en;q=0.5"}, "format_note": "tiny", "asr": 48000, "downloader_options": {"http_chunk_size": 10485760}, "container": "webm_dash", "acodec": "opus", "vcodec": "none", "url": "https://r1---sn-vuxbavcx-5uid.googlevideo.com/videoplayback?expire=1638297138&ei=0hmmYe31DZSBgQf71ZVA&ip=79.129.41.108&id=o-ABsktdzF-pG9E2NRbLDYQWPl2UIjCGgM4wlwCQlIaE1n&itag=251&source=youtube&requiressl=yes&mh=wI&mm=31%2C29&mn=sn-vuxbavcx-5uid%2Csn-4g5lzned&ms=au%2Crdu&mv=m&mvi=1&pl=20&initcwndbps=835000&vprv=1&mime=audio%2Fwebm&ns=HgS-gNV31uknf0hQClv_wCAG&gir=yes&clen=28371181&dur=1761.061&lmt=1620791801154294&mt=1638275337&fvip=1&keepalive=yes&fexp=24001373%2C24007246&beids=23886201&c=WEB&txp=5311222&n=iwfAPWQxtKCDFWIX&sparams=expire%2Cei%2Cip%2Cid%2Citag%2Csource%2Crequiressl%2Cvprv%2Cmime%2Cns%2Cgir%2Cclen%2Cdur%2Clmt&sig=AOq0QJ8wRQIhAOy8D5poMv4LI_y199z5rWagi-MAhBwKObSTFDpPGhKGAiBPIS0_NcZW84HDHu_G7tNnJZKyMouaVjbKDvjbXMot2Q%3D%3D&lsparams=mh%2Cmm%2Cmn%2Cms%2Cmv%2Cmvi%2Cpl%2Cinitcwndbps&lsig=AG3C_xAwRQIhAJ3YCRnjrJHRmXIhc2AAqhxUz4MVxCGdNS758yUcmlX_AiBsP9xwHEfl2NZ82syKirmjYxRSKaUzMYF2y9_LKXYkJg%3D%3D", "format": "251 - audio only (tiny)", "abr": 128.882, "tbr": 128.882, "quality": 0, "protocol": "https", "format_id": "251", "height": null}, {"width": null, "filesize": 28502495, "fps": null, "ext": "m4a", "http_headers": {"Accept-Charset": "ISO-8859-1,utf-8;q=0.7,*;q=0.7", "User-Agent": "Mozilla/5.0 (Windows NT 10.0; Win64; x64) AppleWebKit/537.36 (KHTML, like Gecko) Chrome/74.0.3726.0 Safari/537.36", "Accept": "text/html,application/xhtml+xml,application/xml;q=0.9,*/*;q=0.8", "Accept-Encoding": "gzip, deflate", "Accept-Language": "en-us,en;q=0.5"}, "format_note": "tiny", "asr": 44100, "downloader_options": {"http_chunk_size": 10485760}, "container": "m4a_dash", "acodec": "mp4a.40.2", "vcodec": "none", "url": "https://r1---sn-vuxbavcx-5uid.googlevideo.com/videoplayback?expire=1638297138&ei=0hmmYe31DZSBgQf71ZVA&ip=79.129.41.108&id=o-ABsktdzF-pG9E2NRbLDYQWPl2UIjCGgM4wlwCQlIaE1n&itag=140&source=youtube&requiressl=yes&mh=wI&mm=31%2C29&mn=sn-vuxbavcx-5uid%2Csn-4g5lzned&ms=au%2Crdu&mv=m&mvi=1&pl=20&initcwndbps=835000&vprv=1&mime=audio%2Fmp4&ns=HgS-gNV31uknf0hQClv_wCAG&gir=yes&clen=28502495&dur=1761.094&lmt=1620788116070926&mt=1638275337&fvip=1&keepalive=yes&fexp=24001373%2C24007246&beids=23886201&c=WEB&txp=5311222&n=iwfAPWQxtKCDFWIX&sparams=expire%2Cei%2Cip%2Cid%2Citag%2Csource%2Crequiressl%2Cvprv%2Cmime%2Cns%2Cgir%2Cclen%2Cdur%2Clmt&sig=AOq0QJ8wRQIgIhbIRLMKPeQQeYWt0UHs_UeHEhpTI8Va8bP84BrnCLgCIQDTnYClwj3Buy380eaiBrlTktY7rM2r_K_3-jWdN0K-UA%3D%3D&lsparams=mh%2Cmm%2Cmn%2Cms%2Cmv%2Cmvi%2Cpl%2Cinitcwndbps&lsig=AG3C_xAwRQIhAJ3YCRnjrJHRmXIhc2AAqhxUz4MVxCGdNS758yUcmlX_AiBsP9xwHEfl2NZ82syKirmjYxRSKaUzMYF2y9_LKXYkJg%3D%3D", "format": "140 - audio only (tiny)", "abr": 129.476, "tbr": 129.476, "quality": 0, "protocol": "https", "format_id": "140", "height": null}, {"width": 256, "filesize": 18098160, "fps": 25, "ext": "mp4", "http_headers": {"Accept-Charset": "ISO-8859-1,utf-8;q=0.7,*;q=0.7", "User-Agent": "Mozilla/5.0 (Windows NT 10.0; Win64; x64) AppleWebKit/537.36 (KHTML, like Gecko) Chrome/74.0.3726.0 Safari/537.36", "Accept": "text/html,application/xhtml+xml,application/xml;q=0.9,*/*;q=0.8", "Accept-Encoding": "gzip, deflate", "Accept-Language": "en-us,en;q=0.5"}, "format_note": "144p", "asr": null, "downloader_options": {"http_chunk_size": 10485760}, "container": "mp4_dash", "acodec": "none", "vcodec": "avc1.4d400c", "url": "https://r1---sn-vuxbavcx-5uid.googlevideo.com/videoplayback?expire=1638297138&ei=0hmmYe31DZSBgQf71ZVA&ip=79.129.41.108&id=o-ABsktdzF-pG9E2NRbLDYQWPl2UIjCGgM4wlwCQlIaE1n&itag=160&aitags=133%2C134%2C135%2C160%2C242%2C243%2C244%2C278&source=youtube&requiressl=yes&mh=wI&mm=31%2C29&mn=sn-vuxbavcx-5uid%2Csn-4g5lzned&ms=au%2Crdu&mv=m&mvi=1&pl=20&initcwndbps=835000&vprv=1&mime=video%2Fmp4&ns=HgS-gNV31uknf0hQClv_wCAG&gir=yes&clen=18098160&dur=1761.040&lmt=1620788105548245&mt=1638275337&fvip=1&keepalive=yes&fexp=24001373%2C24007246&beids=23886201&c=WEB&txp=5316222&n=iwfAPWQxtKCDFWIX&sparams=expire%2Cei%2Cip%2Cid%2Caitags%2Csource%2Crequiressl%2Cvprv%2Cmime%2Cns%2Cgir%2Cclen%2Cdur%2Clmt&sig=AOq0QJ8wRQIgdjhjGBs-gvESJ0AnvIT4hs9j6FwtPCyxY9LtY9GLYx4CIQDVVe6pSlD51nWMKbsHaAM6zzHYyNPl43I7FEwHJLjOcA%3D%3D&lsparams=mh%2Cmm%2Cmn%2Cms%2Cmv%2Cmvi%2Cpl%2Cinitcwndbps&lsig=AG3C_xAwRQIhAJ3YCRnjrJHRmXIhc2AAqhxUz4MVxCGdNS758yUcmlX_AiBsP9xwHEfl2NZ82syKirmjYxRSKaUzMYF2y9_LKXYkJg%3D%3D", "format": "160 - 256x144 (144p)", "tbr": 82.215, "quality": 0, "protocol": "https", "vbr": 82.215, "format_id": "160", "height": 144}, {"width": 256, "filesize": 19430782, "fps": 25, "ext": "webm", "http_headers": {"Accept-Charset": "ISO-8859-1,utf-8;q=0.7,*;q=0.7", "User-Agent": "Mozilla/5.0 (Windows NT 10.0; Win64; x64) AppleWebKit/537.36 (KHTML, like Gecko) Chrome/74.0.3726.0 Safari/537.36", "Accept": "text/html,application/xhtml+xml,application/xml;q=0.9,*/*;q=0.8", "Accept-Encoding": "gzip, deflate", "Accept-Language": "en-us,en;q=0.5"}, "format_note": "144p", "asr": null, "downloader_options": {"http_chunk_size": 10485760}, "container": "webm_dash", "acodec": "none", "vcodec": "vp9", "url": "https://r1---sn-vuxbavcx-5uid.googlevideo.com/videoplayback?expire=1638297138&ei=0hmmYe31DZSBgQf71ZVA&ip=79.129.41.108&id=o-ABsktdzF-pG9E2NRbLDYQWPl2UIjCGgM4wlwCQlIaE1n&itag=278&aitags=133%2C134%2C135%2C160%2C242%2C243%2C244%2C278&source=youtube&requiressl=yes&mh=wI&mm=31%2C29&mn=sn-vuxbavcx-5uid%2Csn-4g5lzned&ms=au%2Crdu&mv=m&mvi=1&pl=20&initcwndbps=835000&vprv=1&mime=video%2Fwebm&ns=HgS-gNV31uknf0hQClv_wCAG&gir=yes&clen=19430782&dur=1761.040&lmt=1620793575457365&mt=1638275337&fvip=1&keepalive=yes&fexp=24001373%2C24007246&beids=23886201&c=WEB&txp=5311222&n=iwfAPWQxtKCDFWIX&sparams=expire%2Cei%2Cip%2Cid%2Caitags%2Csource%2Crequiressl%2Cvprv%2Cmime%2Cns%2Cgir%2Cclen%2Cdur%2Clmt&sig=AOq0QJ8wRQIgeZrcG9nZEVCam-n1VcDEaiJkyDBz0cLoBKcxXeKLe_MCIQDm5-Wu6owvPtfwF8Y6tb4W5OIdP0uwz0YuKTBNGweELw%3D%3D&lsparams=mh%2Cmm%2Cmn%2Cms%2Cmv%2Cmvi%2Cpl%2Cinitcwndbps&lsig=AG3C_xAwRQIhAJ3YCRnjrJHRmXIhc2AAqhxUz4MVxCGdNS758yUcmlX_AiBsP9xwHEfl2NZ82syKirmjYxRSKaUzMYF2y9_LKXYkJg%3D%3D", "format": "278 - 256x144 (144p)", "tbr": 88.269, "quality": 0, "protocol": "https", "vbr": 88.269, "format_id": "278", "height": 144}, {"width": 426, "filesize": 26573606, "fps": 25, "ext": "webm", "http_headers": {"Accept-Charset": "ISO-8859-1,utf-8;q=0.7,*;q=0.7", "User-Agent": "Mozilla/5.0 (Windows NT 10.0; Win64; x64) AppleWebKit/537.36 (KHTML, like Gecko) Chrome/74.0.3726.0 Safari/537.36", "Accept": "text/html,application/xhtml+xml,application/xml;q=0.9,*/*;q=0.8", "Accept-Encoding": "gzip, deflate", "Accept-Language": "en-us,en;q=0.5"}, "format_note": "240p", "asr": null, "downloader_options": {"http_chunk_size": 10485760}, "container": "webm_dash", "acodec": "none", "vcodec": "vp9", "url": "https://r1---sn-vuxbavcx-5uid.googlevideo.com/videoplayback?expire=1638297138&ei=0hmmYe31DZSBgQf71ZVA&ip=79.129.41.108&id=o-ABsktdzF-pG9E2NRbLDYQWPl2UIjCGgM4wlwCQlIaE1n&itag=242&aitags=133%2C134%2C135%2C160%2C242%2C243%2C244%2C278&source=youtube&requiressl=yes&mh=wI&mm=31%2C29&mn=sn-vuxbavcx-5uid%2Csn-4g5lzned&ms=au%2Crdu&mv=m&mvi=1&pl=20&initcwndbps=835000&vprv=1&mime=video%2Fwebm&ns=HgS-gNV31uknf0hQClv_wCAG&gir=yes&clen=26573606&dur=1761.040&lmt=1620793575453968&mt=1638275337&fvip=1&keepalive=yes&fexp=24001373%2C24007246&beids=23886201&c=WEB&txp=5311222&n=iwfAPWQxtKCDFWIX&sparams=expire%2Cei%2Cip%2Cid%2Caitags%2Csource%2Crequiressl%2Cvprv%2Cmime%2Cns%2Cgir%2Cclen%2Cdur%2Clmt&sig=AOq0QJ8wRAIgc9o45ZiRwq2FnNuIatQac9r4isN0RuiXYkGT3XamcwACIHT4wQ2VZGf_Afzz3BeeTeG8Pj6Bf7jj97T5PS9ov13Q&lsparams=mh%2Cmm%2Cmn%2Cms%2Cmv%2Cmvi%2Cpl%2Cinitcwndbps&lsig=AG3C_xAwRQIhAJ3YCRnjrJHRmXIhc2AAqhxUz4MVxCGdNS758yUcmlX_AiBsP9xwHEfl2NZ82syKirmjYxRSKaUzMYF2y9_LKXYkJg%3D%3D", "format": "242 - 426x240 (240p)", "tbr": 120.717, "quality": 1, "protocol": "https", "vbr": 120.717, "format_id": "242", "height": 240}, {"width": 426, "filesize": 39902482, "fps": 25, "ext": "mp4", "http_headers": {"Accept-Charset": "ISO-8859-1,utf-8;q=0.7,*;q=0.7", "User-Agent": "Mozilla/5.0 (Windows NT 10.0; Win64; x64) AppleWebKit/537.36 (KHTML, like Gecko) Chrome/74.0.3726.0 Safari/537.36", "Accept": "text/html,application/xhtml+xml,application/xml;q=0.9,*/*;q=0.8", "Accept-Encoding": "gzip, deflate", "Accept-Language": "en-us,en;q=0.5"}, "format_note": "240p", "asr": null, "downloader_options": {"http_chunk_size": 10485760}, "container": "mp4_dash", "acodec": "none", "vcodec": "avc1.4d4015", "url": "https://r1---sn-vuxbavcx-5uid.googlevideo.com/videoplayback?expire=1638297138&ei=0hmmYe31DZSBgQf71ZVA&ip=79.129.41.108&id=o-ABsktdzF-pG9E2NRbLDYQWPl2UIjCGgM4wlwCQlIaE1n&itag=133&aitags=133%2C134%2C135%2C160%2C242%2C243%2C244%2C278&source=youtube&requiressl=yes&mh=wI&mm=31%2C29&mn=sn-vuxbavcx-5uid%2Csn-4g5lzned&ms=au%2Crdu&mv=m&mvi=1&pl=20&initcwndbps=835000&vprv=1&mime=video%2Fmp4&ns=HgS-gNV31uknf0hQClv_wCAG&gir=yes&clen=39902482&dur=1761.040&lmt=1620788105599006&mt=1638275337&fvip=1&keepalive=yes&fexp=24001373%2C24007246&beids=23886201&c=WEB&txp=5316222&n=iwfAPWQxtKCDFWIX&sparams=expire%2Cei%2Cip%2Cid%2Caitags%2Csource%2Crequiressl%2Cvprv%2Cmime%2Cns%2Cgir%2Cclen%2Cdur%2Clmt&sig=AOq0QJ8wRgIhANRg9155-8yX-NXhU5DoE48Z8c0VTlkq15WNmnfiBF6pAiEAtIGJZr6PRi1mbKzFm5971cDFO-VW1tPBe-HAf_kDPgA%3D&lsparams=mh%2Cmm%2Cmn%2Cms%2Cmv%2Cmvi%2Cpl%2Cinitcwndbps&lsig=AG3C_xAwRQIhAJ3YCRnjrJHRmXIhc2AAqhxUz4MVxCGdNS758yUcmlX_AiBsP9xwHEfl2NZ82syKirmjYxRSKaUzMYF2y9_LKXYkJg%3D%3D", "format": "133 - 426x240 (240p)", "tbr": 181.267, "quality": 1, "protocol": "https", "vbr": 181.267, "format_id": "133", "height": 240}, {"width": 640, "filesize": 48952232, "fps": 25, "ext": "webm", "http_headers": {"Accept-Charset": "ISO-8859-1,utf-8;q=0.7,*;q=0.7", "User-Agent": "Mozilla/5.0 (Windows NT 10.0; Win64; x64) AppleWebKit/537.36 (KHTML, like Gecko) Chrome/74.0.3726.0 Safari/537.36", "Accept": "text/html,application/xhtml+xml,application/xml;q=0.9,*/*;q=0.8", "Accept-Encoding": "gzip, deflate", "Accept-Language": "en-us,en;q=0.5"}, "format_note": "360p", "asr": null, "downloader_options": {"http_chunk_size": 10485760}, "container": "webm_dash", "acodec": "none", "vcodec": "vp9", "url": "https://r1---sn-vuxbavcx-5uid.googlevideo.com/videoplayback?expire=1638297138&ei=0hmmYe31DZSBgQf71ZVA&ip=79.129.41.108&id=o-ABsktdzF-pG9E2NRbLDYQWPl2UIjCGgM4wlwCQlIaE1n&itag=243&aitags=133%2C134%2C135%2C160%2C242%2C243%2C244%2C278&source=youtube&requiressl=yes&mh=wI&mm=31%2C29&mn=sn-vuxbavcx-5uid%2Csn-4g5lzned&ms=au%2Crdu&mv=m&mvi=1&pl=20&initcwndbps=835000&vprv=1&mime=video%2Fwebm&ns=HgS-gNV31uknf0hQClv_wCAG&gir=yes&clen=48952232&dur=1761.040&lmt=1620793575449073&mt=1638275337&fvip=1&keepalive=yes&fexp=24001373%2C24007246&beids=23886201&c=WEB&txp=5311222&n=iwfAPWQxtKCDFWIX&sparams=expire%2Cei%2Cip%2Cid%2Caitags%2Csource%2Crequiressl%2Cvprv%2Cmime%2Cns%2Cgir%2Cclen%2Cdur%2Clmt&sig=AOq0QJ8wRQIhANOCLqlJvNxwGCKo6vkN9SZIH5aXZLcSIPBC9w1hwmn6AiBYfGmstPT6RmVnxOAS_fu5qB2xQqW53lGx9A5eMPRoqg%3D%3D&lsparams=mh%2Cmm%2Cmn%2Cms%2Cmv%2Cmvi%2Cpl%2Cinitcwndbps&lsig=AG3C_xAwRQIhAJ3YCRnjrJHRmXIhc2AAqhxUz4MVxCGdNS758yUcmlX_AiBsP9xwHEfl2NZ82syKirmjYxRSKaUzMYF2y9_LKXYkJg%3D%3D", "format": "243 - 640x360 (360p)", "tbr": 222.378, "quality": 2, "protocol": "https", "vbr": 222.378, "format_id": "243", "height": 360}, {"width": 640, "filesize": 75332585, "fps": 25, "ext": "mp4", "http_headers": {"Accept-Charset": "ISO-8859-1,utf-8;q=0.7,*;q=0.7", "User-Agent": "Mozilla/5.0 (Windows NT 10.0; Win64; x64) AppleWebKit/537.36 (KHTML, like Gecko) Chrome/74.0.3726.0 Safari/537.36", "Accept": "text/html,application/xhtml+xml,application/xml;q=0.9,*/*;q=0.8", "Accept-Encoding": "gzip, deflate", "Accept-Language": "en-us,en;q=0.5"}, "format_note": "360p", "asr": null, "downloader_options": {"http_chunk_size": 10485760}, "container": "mp4_dash", "acodec": "none", "vcodec": "avc1.4d401e", "url": "https://r1---sn-vuxbavcx-5uid.googlevideo.com/videoplayback?expire=1638297138&ei=0hmmYe31DZSBgQf71ZVA&ip=79.129.41.108&id=o-ABsktdzF-pG9E2NRbLDYQWPl2UIjCGgM4wlwCQlIaE1n&itag=134&aitags=133%2C134%2C135%2C160%2C242%2C243%2C244%2C278&source=youtube&requiressl=yes&mh=wI&mm=31%2C29&mn=sn-vuxbavcx-5uid%2Csn-4g5lzned&ms=au%2Crdu&mv=m&mvi=1&pl=20&initcwndbps=835000&vprv=1&mime=video%2Fmp4&ns=HgS-gNV31uknf0hQClv_wCAG&gir=yes&clen=75332585&dur=1761.040&lmt=1620788105546401&mt=1638275337&fvip=1&keepalive=yes&fexp=24001373%2C24007246&beids=23886201&c=WEB&txp=5316222&n=iwfAPWQxtKCDFWIX&sparams=expire%2Cei%2Cip%2Cid%2Caitags%2Csource%2Crequiressl%2Cvprv%2Cmime%2Cns%2Cgir%2Cclen%2Cdur%2Clmt&sig=AOq0QJ8wRAIgcuRcBgLF-QvarC_l8YgirMWIyhdcTPuqYmpM5QArlQoCIAyQl8Pp3_ffIEONGF2WkmqcOjigr_puH1INVxkkz3pB&lsparams=mh%2Cmm%2Cmn%2Cms%2Cmv%2Cmvi%2Cpl%2Cinitcwndbps&lsig=AG3C_xAwRQIhAJ3YCRnjrJHRmXIhc2AAqhxUz4MVxCGdNS758yUcmlX_AiBsP9xwHEfl2NZ82syKirmjYxRSKaUzMYF2y9_LKXYkJg%3D%3D", "format": "134 - 640x360 (360p)", "tbr": 342.218, "quality": 2, "protocol": "https", "vbr": 342.218, "format_id": "134", "height": 360}, {"width": 854, "filesize": 86713173, "fps": 25, "ext": "webm", "http_headers": {"Accept-Charset": "ISO-8859-1,utf-8;q=0.7,*;q=0.7", "User-Agent": "Mozilla/5.0 (Windows NT 10.0; Win64; x64) AppleWebKit/537.36 (KHTML, like Gecko) Chrome/74.0.3726.0 Safari/537.36", "Accept": "text/html,application/xhtml+xml,application/xml;q=0.9,*/*;q=0.8", "Accept-Encoding": "gzip, deflate", "Accept-Language": "en-us,en;q=0.5"}, "format_note": "480p", "asr": null, "downloader_options": {"http_chunk_size": 10485760}, "container": "webm_dash", "acodec": "none", "vcodec": "vp9", "url": "https://r1---sn-vuxbavcx-5uid.googlevideo.com/videoplayback?expire=1638297138&ei=0hmmYe31DZSBgQf71ZVA&ip=79.129.41.108&id=o-ABsktdzF-pG9E2NRbLDYQWPl2UIjCGgM4wlwCQlIaE1n&itag=244&aitags=133%2C134%2C135%2C160%2C242%2C243%2C244%2C278&source=youtube&requiressl=yes&mh=wI&mm=31%2C29&mn=sn-vuxbavcx-5uid%2Csn-4g5lzned&ms=au%2Crdu&mv=m&mvi=1&pl=20&initcwndbps=835000&vprv=1&mime=video%2Fwebm&ns=HgS-gNV31uknf0hQClv_wCAG&gir=yes&clen=86713173&dur=1761.040&lmt=1620793575457334&mt=1638275337&fvip=1&keepalive=yes&fexp=24001373%2C24007246&beids=23886201&c=WEB&txp=5311222&n=iwfAPWQxtKCDFWIX&sparams=expire%2Cei%2Cip%2Cid%2Caitags%2Csource%2Crequiressl%2Cvprv%2Cmime%2Cns%2Cgir%2Cclen%2Cdur%2Clmt&sig=AOq0QJ8wRAIgBEITotgEzfBMvEhZHyLLNGyy6_Fa-P-cqy-9il-U-5gCIGsu3tmH5q3Dryosj-GkQXoOjZHAN6Jj2xGoSj8dJcGQ&lsparams=mh%2Cmm%2Cmn%2Cms%2Cmv%2Cmvi%2Cpl%2Cinitcwndbps&lsig=AG3C_xAwRQIhAJ3YCRnjrJHRmXIhc2AAqhxUz4MVxCGdNS758yUcmlX_AiBsP9xwHEfl2NZ82syKirmjYxRSKaUzMYF2y9_LKXYkJg%3D%3D", "format": "244 - 854x480 (480p)", "tbr": 393.918, "quality": 3, "protocol": "https", "vbr": 393.918, "format_id": "244", "height": 480}, {"width": 854, "filesize": 147648315, "fps": 25, "ext": "mp4", "http_headers": {"Accept-Charset": "ISO-8859-1,utf-8;q=0.7,*;q=0.7", "User-Agent": "Mozilla/5.0 (Windows NT 10.0; Win64; x64) AppleWebKit/537.36 (KHTML, like Gecko) Chrome/74.0.3726.0 Safari/537.36", "Accept": "text/html,application/xhtml+xml,application/xml;q=0.9,*/*;q=0.8", "Accept-Encoding": "gzip, deflate", "Accept-Language": "en-us,en;q=0.5"}, "format_note": "480p", "asr": null, "downloader_options": {"http_chunk_size": 10485760}, "container": "mp4_dash", "acodec": "none", "vcodec": "avc1.4d401e", "url": "https://r1---sn-vuxbavcx-5uid.googlevideo.com/videoplayback?expire=1638297138&ei=0hmmYe31DZSBgQf71ZVA&ip=79.129.41.108&id=o-ABsktdzF-pG9E2NRbLDYQWPl2UIjCGgM4wlwCQlIaE1n&itag=135&aitags=133%2C134%2C135%2C160%2C242%2C243%2C244%2C278&source=youtube&requiressl=yes&mh=wI&mm=31%2C29&mn=sn-vuxbavcx-5uid%2Csn-4g5lzned&ms=au%2Crdu&mv=m&mvi=1&pl=20&initcwndbps=835000&vprv=1&mime=video%2Fmp4&ns=HgS-gNV31uknf0hQClv_wCAG&gir=yes&clen=147648315&dur=1761.040&lmt=1620788105558702&mt=1638275337&fvip=1&keepalive=yes&fexp=24001373%2C24007246&beids=23886201&c=WEB&txp=5316222&n=iwfAPWQxtKCDFWIX&sparams=expire%2Cei%2Cip%2Cid%2Caitags%2Csource%2Crequiressl%2Cvprv%2Cmime%2Cns%2Cgir%2Cclen%2Cdur%2Clmt&sig=AOq0QJ8wRQIhAKkXbGR7wEfR-dHdqFaqp__gHK4uI5ZAJ0sNE_iHw8IWAiBbw4RGJFe82l4xXHDQvMsv32yJmNmYGjHN4nLEQygZtQ%3D%3D&lsparams=mh%2Cmm%2Cmn%2Cms%2Cmv%2Cmvi%2Cpl%2Cinitcwndbps&lsig=AG3C_xAwRQIhAJ3YCRnjrJHRmXIhc2AAqhxUz4MVxCGdNS758yUcmlX_AiBsP9xwHEfl2NZ82syKirmjYxRSKaUzMYF2y9_LKXYkJg%3D%3D", "format": "135 - 854x480 (480p)", "tbr": 670.732, "quality": 3, "protocol": "https", "vbr": 670.732, "format_id": "135", "height": 480}, {"width": 640, "filesize": 95170266, "fps": 25, "ext": "mp4", "http_headers": {"Accept-Charset": "ISO-8859-1,utf-8;q=0.7,*;q=0.7", "User-Agent": "Mozilla/5.0 (Windows NT 10.0; Win64; x64) AppleWebKit/537.36 (KHTML, like Gecko) Chrome/74.0.3726.0 Safari/537.36", "Accept": "text/html,application/xhtml+xml,application/xml;q=0.9,*/*;q=0.8", "Accept-Encoding": "gzip, deflate", "Accept-Language": "en-us,en;q=0.5"}, "format_note": "360p", "asr": 44100, "acodec": "mp4a.40.2", "vcodec": "avc1.42001E", "url": "https://r1---sn-vuxbavcx-5uid.googlevideo.com/videoplayback?expire=1638297138&ei=0hmmYe31DZSBgQf71ZVA&ip=79.129.41.108&id=o-ABsktdzF-pG9E2NRbLDYQWPl2UIjCGgM4wlwCQlIaE1n&itag=18&source=youtube&requiressl=yes&mh=wI&mm=31%2C29&mn=sn-vuxbavcx-5uid%2Csn-4g5lzned&ms=au%2Crdu&mv=m&mvi=1&pl=20&initcwndbps=835000&vprv=1&mime=video%2Fmp4&ns=LiDoE6aoOtjFCx4WnuT3XecG&gir=yes&clen=95170266&ratebypass=yes&dur=1761.094&lmt=1620788153428911&mt=1638275337&fvip=1&fexp=24001373%2C24007246&beids=23886201&c=WEB&txp=5310222&n=3PHBRZkKVae45oic&sparams=expire%2Cei%2Cip%2Cid%2Citag%2Csource%2Crequiressl%2Cvprv%2Cmime%2Cns%2Cgir%2Cclen%2Cratebypass%2Cdur%2Clmt&sig=AOq0QJ8wRQIhAOp44SKgj85LYGWgG0EKPn0w3VlIeCZ4vWYKbFbbDvTkAiALDhK3gmnbbfwz-sqtqLqF3dF9tsqhD4FBv7jOlPlJaw%3D%3D&lsparams=mh%2Cmm%2Cmn%2Cms%2Cmv%2Cmvi%2Cpl%2Cinitcwndbps&lsig=AG3C_xAwRQIhAJ3YCRnjrJHRmXIhc2AAqhxUz4MVxCGdNS758yUcmlX_AiBsP9xwHEfl2NZ82syKirmjYxRSKaUzMYF2y9_LKXYkJg%3D%3D", "format": "18 - 640x360 (360p)", "tbr": 432.323, "quality": 2, "protocol": "https", "format_id": "18", "height": 360}], "tbr": 432.323, "playlist_index": null, "webpage_url": "https://www.youtube.com/watch?v=4SqMWpCcP50", "channel_id": "UCW6JA9R8FtNXlwN0yZ_ILbQ", "thumbnails": [{"url": "https://i.ytimg.com/vi/4SqMWpCcP50/hqdefault.jpg?sqp=-oaymwEbCKgBEF5IVfKriqkDDggBFQAAiEIYAXABwAEG&rs=AOn4CLAy2rPy3WTmdyqRjiv6YVC4XNu5Rw", "width": 168, "id": "0", "height": 94, "resolution": "168x94"}, {"url": "https://i.ytimg.com/vi/4SqMWpCcP50/hqdefault.jpg?sqp=-oaymwEbCMQBEG5IVfKriqkDDggBFQAAiEIYAXABwAEG&rs=AOn4CLDPOp6EGHDyO5gAWalnx-1xXtgEJg", "width": 196, "id": "1", "height": 110, "resolution": "196x110"}, {"url": "https://i.ytimg.com/vi/4SqMWpCcP50/hqdefault.jpg?sqp=-oaymwEcCPYBEIoBSFXyq4qpAw4IARUAAIhCGAFwAcABBg==&rs=AOn4CLD0gnv4y8RlYyh796jhgDeywHCCjg", "width": 246, "id": "2", "height": 138, "resolution": "246x138"}, {"url": "https://i.ytimg.com/vi/4SqMWpCcP50/hqdefault.jpg?sqp=-oaymwEcCNACELwBSFXyq4qpAw4IARUAAIhCGAFwAcABBg==&rs=AOn4CLBC1Ksidt3ER5WJ0XgP6o9xtRsSNw", "width": 336, "id": "3", "height": 188, "resolution": "336x188"}], "duration": 1761, "id": "4SqMWpCcP50", "playlist": null, "acodec": "mp4a.40.2", "tags": ["Stephane Grappelli", "Martin Taylor", "Jazz", "Django Reinhardt", "Paper Moon", "David Peat", "Leman", "Ayr", "ExS", "BBC Scotland", "Sweet Georgia Brown", "Louis Armstrong", "Willow Weep For Me", "Duke Ellington", "Yehudi Menhuin", "David Grisman", "Barney Kessel", "Paul Simon", "Oscar Peterson", "Michel Legrand", "BBC Arts", "BBC Documentary", "BBC Music", "Jazz Violin", "Jazz Guitar", "\u82f1\u56fd\u5e7f\u64ad\u516c\u53f8\u7eaa\u5f55\u7247", "\u82f1\u56fd\u5e7f\u64ad\u516c\u53f8\u827a\u672f", "\u0628\u064a \u0628\u064a \u0633\u064a \u0648\u062b\u0627\u0626\u0642\u064a"], "height": 360, "format_note": "360p", "ext": "mp4", "upload_date": "20180625", "display_id": "4SqMWpCcP50", "like_count": 225, "fulltitle": "MEETING GRAPPELLI - BBC Arts Documentary 1993", "age_limit": 0, "average_rating": 4.9647579, "title": "MEETING GRAPPELLI - BBC Arts Documentary 1993", "width": 640, "filesize": 95170266, "categories": ["Music"], "vcodec": "avc1.42001E", "is_live": null, "url": "https://r1---sn-vuxbavcx-5uid.googlevideo.com/videoplayback?expire=1638297138&ei=0hmmYe31DZSBgQf71ZVA&ip=79.129.41.108&id=o-ABsktdzF-pG9E2NRbLDYQWPl2UIjCGgM4wlwCQlIaE1n&itag=18&source=youtube&requiressl=yes&mh=wI&mm=31%2C29&mn=sn-vuxbavcx-5uid%2Csn-4g5lzned&ms=au%2Crdu&mv=m&mvi=1&pl=20&initcwndbps=835000&vprv=1&mime=video%2Fmp4&ns=LiDoE6aoOtjFCx4WnuT3XecG&gir=yes&clen=95170266&ratebypass=yes&dur=1761.094&lmt=1620788153428911&mt=1638275337&fvip=1&fexp=24001373%2C24007246&beids=23886201&c=WEB&txp=5310222&n=3PHBRZkKVae45oic&sparams=expire%2Cei%2Cip%2Cid%2Citag%2Csource%2Crequiressl%2Cvprv%2Cmime%2Cns%2Cgir%2Cclen%2Cratebypass%2Cdur%2Clmt&sig=AOq0QJ8wRQIhAOp44SKgj85LYGWgG0EKPn0w3VlIeCZ4vWYKbFbbDvTkAiALDhK3gmnbbfwz-sqtqLqF3dF9tsqhD4FBv7jOlPlJaw%3D%3D&lsparams=mh%2Cmm%2Cmn%2Cms%2Cmv%2Cmvi%2Cpl%2Cinitcwndbps&lsig=AG3C_xAwRQIhAJ3YCRnjrJHRmXIhc2AAqhxUz4MVxCGdNS758yUcmlX_AiBsP9xwHEfl2NZ82syKirmjYxRSKaUzMYF2y9_LKXYkJg%3D%3D", "thumbnail": "https://i.ytimg.com/vi/4SqMWpCcP50/hqdefault.jpg?sqp=-oaymwEcCNACELwBSFXyq4qpAw4IARUAAIhCGAFwAcABBg==&rs=AOn4CLBC1Ksidt3ER5WJ0XgP6o9xtRsSNw", "quality": 2, "protocol": "https", "channel": "LEMAN PRODUCTIONS Ltd", "http_headers": {"Accept-Charset": "ISO-8859-1,utf-8;q=0.7,*;q=0.7", "User-Agent": "Mozilla/5.0 (Windows NT 10.0; Win64; x64) AppleWebKit/537.36 (KHTML, like Gecko) Chrome/74.0.3726.0 Safari/537.36", "Accept": "text/html,application/xhtml+xml,application/xml;q=0.9,*/*;q=0.8", "Accept-Encoding": "gzip, deflate", "Accept-Language": "en-us,en;q=0.5"}, "fps": 25, "uploader_id": "UCW6JA9R8FtNXlwN0yZ_ILbQ", "asr": 44100, "uploader_url": "http://www.youtube.com/channel/UCW6JA9R8FtNXlwN0yZ_ILbQ", "format_id": "18", "view_count": 9929, "description": "In the summer of his 85th year, Stephane Grappelli visited Ayr to see his friend - guitarist Martin Taylor.\n\n\u2018This affectionate and unpretentious programme captures beautifully the special relationship that Stephane had with his wonderful guitarist.\u201d Stephane Grappelli - A Life in Jazz, author Paul Balmer.\n\n\nFilmed in 1993 and first shown on BBC Scotland\u2019s \u2018ExS\u2019, Music and Arts Series. Producer - Trevor Davies for Skyline Film and Television.\n\nDirectors - David Peat (+ 2nd unit), Jan Leman (+ Film Editor)\nStandard 16mm Eastmancolour, 2 camera, stereo.\n\nPosted in fond remembrance of David, and all that he instilled.\n\nDavid Peat - Film-maker and Photographer 1947- 2012\n\nwww.bbc.co.uk/news/uk-scotland-17741893\n\nhttp://www.heraldscotland.com/news/13055078.Billy_Connolly___I_owe_David_so_much_-_I_will_miss_him_/\n\n\nhttps://www.amazon.com/Stephane-Grappelli-Life-Paul-Balmer-ebook/dp/B003Q6CQUW/ref=sr_1_4?s=books&ie=UTF8&qid=1529933280&sr=1-4&keywords=stephane+grappelli\n\nhttps://www.amazon.com/R\u00e9union-Stephane-Grappelli/dp/B00U8ABLC8/ref=sr_1_1?ie=UTF8&qid=1529933374&sr=8-1&keywords=stephane+grappelli+martin+taylor\n\nhttps://martintaylor.com\n\nhttp://www.skyline.uk.com", "format": "18 - 640x360 (360p)", "extractor_key": "Youtube", "extractor": "youtube"}