{"format": "22 - 1280x720 (720p)", "like_count": 11, "is_live": null, "extractor": "youtube", "asr": 44100, "webpage_url": "https://www.youtube.com/watch?v=xm7rBk137Zo", "formats": [{"tbr": 49.956, "container": "m4a_dash", "format_id": "139", "http_headers": {"Accept-Charset": "ISO-8859-1,utf-8;q=0.7,*;q=0.7", "Accept-Language": "en-us,en;q=0.5", "User-Agent": "Mozilla/5.0 (Windows NT 10.0; Win64; x64) AppleWebKit/537.36 (KHTML, like Gecko) Chrome/73.0.3683.112 Safari/537.36", "Accept": "text/html,application/xhtml+xml,application/xml;q=0.9,*/*;q=0.8", "Accept-Encoding": "gzip, deflate"}, "acodec": "mp4a.40.5", "format": "139 - audio only (DASH audio)", "asr": 22050, "fragments": [{"path": "range/0-593"}, {"duration": 5.016, "path": "range/1106-31322"}, {"duration": 5.015, "path": "range/31323-61395"}, {"duration": 4.969, "path": "range/61396-90931"}, {"duration": 5.016, "path": "range/90932-120684"}, {"duration": 5.015, "path": "range/120685-150652"}, {"duration": 4.969, "path": "range/150653-180271"}, {"duration": 5.016, "path": "range/180272-210034"}, {"duration": 5.015, "path": "range/210035-240014"}, {"duration": 4.969, "path": "range/240015-269568"}, {"duration": 5.016, "path": "range/269569-299321"}, {"duration": 5.015, "path": "range/299322-329391"}, {"duration": 4.969, "path": "range/329392-358848"}, {"duration": 5.016, "path": "range/358849-388772"}, {"duration": 5.015, "path": "range/388773-418579"}, {"duration": 4.969, "path": "range/418580-448221"}, {"duration": 5.016, "path": "range/448222-478124"}, {"duration": 5.015, "path": "range/478125-507830"}, {"duration": 4.97, "path": "range/507831-537538"}, {"duration": 5.015, "path": "range/537539-567341"}, {"duration": 5.016, "path": "range/567342-597432"}, {"duration": 4.969, "path": "range/597433-626872"}, {"duration": 5.015, "path": "range/626873-656828"}, {"duration": 5.016, "path": "range/656829-686518"}, {"duration": 4.969, "path": "range/686519-716306"}, {"duration": 5.015, "path": "range/716307-745963"}, {"duration": 5.016, "path": "range/745964-775871"}, {"duration": 4.969, "path": "range/775872-805366"}, {"duration": 5.015, "path": "range/805367-835475"}, {"duration": 5.016, "path": "range/835476-865241"}, {"duration": 4.969, "path": "range/865242-894787"}, {"duration": 5.015, "path": "range/894788-924709"}, {"duration": 5.016, "path": "range/924710-954638"}, {"duration": 4.969, "path": "range/954639-984335"}, {"duration": 5.015, "path": "range/984336-1014100"}, {"duration": 5.016, "path": "range/1014101-1043935"}, {"duration": 4.969, "path": "range/1043936-1073679"}, {"duration": 5.016, "path": "range/1073680-1103729"}, {"duration": 5.015, "path": "range/1103730-1133578"}, {"duration": 4.969, "path": "range/1133579-1162890"}, {"duration": 1.207, "path": "range/1162891-1169841"}], "manifest_url": "https://manifest.googlevideo.com/api/manifest/dash/expire/1638295021/ei/jRGmYYLMLpOa-gb_uZeYBA/ip/79.129.41.108/id/c66eeb064d77ed9a/source/youtube/requiressl/yes/playback_host/r1---sn-vuxbavcx-5uiee.googlevideo.com/mh/ep/mm/31%2C29/mn/sn-vuxbavcx-5uiee%2Csn-4g5lzner/ms/au%2Crdu/mv/m/mvi/1/pl/20/hfr/all/as/fmp4_audio_clear%2Cwebm_audio_clear%2Cwebm2_audio_clear%2Cfmp4_sd_hd_clear%2Cwebm2_sd_hd_clear/initcwndbps/862500/vprv/1/mt/1638272935/fvip/1/keepalive/yes/fexp/24001373%2C24007246/itag/0/sparams/expire%2Cei%2Cip%2Cid%2Csource%2Crequiressl%2Chfr%2Cas%2Cvprv%2Citag/sig/AOq0QJ8wRQIgBg5L9VNZgI-V1InavELG4dBggS-g10tUMx1DQA9MLhoCIQDnMQDQFjMdXV0sQNk395Y-wTQBU6PwCdQ7ioIy67Hhxg%3D%3D/lsparams/playback_host%2Cmh%2Cmm%2Cmn%2Cms%2Cmv%2Cmvi%2Cpl%2Cinitcwndbps/lsig/AG3C_xAwRQIgbKLa6yYrXhf_Rsup11R-BBJjVSJfUFkqzM62MEGu-rkCIQCg97PRBxRiiLfZrhscwKF7QLpNMFt7R3bo4JUPjGtAXg%3D%3D", "fps": null, "protocol": "http_dash_segments", "url": "https://manifest.googlevideo.com/api/manifest/dash/expire/1638295021/ei/jRGmYYLMLpOa-gb_uZeYBA/ip/79.129.41.108/id/c66eeb064d77ed9a/source/youtube/requiressl/yes/playback_host/r1---sn-vuxbavcx-5uiee.googlevideo.com/mh/ep/mm/31%2C29/mn/sn-vuxbavcx-5uiee%2Csn-4g5lzner/ms/au%2Crdu/mv/m/mvi/1/pl/20/hfr/all/as/fmp4_audio_clear%2Cwebm_audio_clear%2Cwebm2_audio_clear%2Cfmp4_sd_hd_clear%2Cwebm2_sd_hd_clear/initcwndbps/862500/vprv/1/mt/1638272935/fvip/1/keepalive/yes/fexp/24001373%2C24007246/itag/0/sparams/expire%2Cei%2Cip%2Cid%2Csource%2Crequiressl%2Chfr%2Cas%2Cvprv%2Citag/sig/AOq0QJ8wRQIgBg5L9VNZgI-V1InavELG4dBggS-g10tUMx1DQA9MLhoCIQDnMQDQFjMdXV0sQNk395Y-wTQBU6PwCdQ7ioIy67Hhxg%3D%3D/lsparams/playback_host%2Cmh%2Cmm%2Cmn%2Cms%2Cmv%2Cmvi%2Cpl%2Cinitcwndbps/lsig/AG3C_xAwRQIgbKLa6yYrXhf_Rsup11R-BBJjVSJfUFkqzM62MEGu-rkCIQCg97PRBxRiiLfZrhscwKF7QLpNMFt7R3bo4JUPjGtAXg%3D%3D", "format_note": "DASH audio", "fragment_base_url": "https://r1---sn-vuxbavcx-5uiee.googlevideo.com/videoplayback/expire/1638295021/ei/jRGmYYLMLpOa-gb_uZeYBA/ip/79.129.41.108/id/c66eeb064d77ed9a/itag/139/source/youtube/requiressl/yes/mh/ep/mm/31,29/mn/sn-vuxbavcx-5uiee,sn-4g5lzner/ms/au,rdu/mv/m/mvi/1/pl/20/initcwndbps/862500/vprv/1/ratebypass/yes/mime/audio%2Fmp4/otfp/1/gir/yes/clen/1169842/lmt/1528053172987277/dur/196.208/mt/1638272935/fvip/1/keepalive/yes/fexp/24001373,24007246/sparams/expire,ei,ip,id,itag,source,requiressl,vprv,ratebypass,mime,otfp,gir,clen,lmt,dur/sig/AOq0QJ8wRQIhAI_uM0-d3q97T7oZLeki8ggQA4384ASlx00axiL7cAGaAiAEhuONLyDFblYxUN-KjgnmxnN6NbA6ZScPwUHdAGvhJg%3D%3D/lsparams/mh,mm,mn,ms,mv,mvi,pl,initcwndbps/lsig/AG3C_xAwRQIgFSlOT_wndfd6asMR-fLIWSf0fzRipGOtnzopOeKtE9ICIQCjBmTVsbLrAkwdDH_BqM0JSF3s7Xc5NfxYF4vbu87xIg%3D%3D/", "width": null, "language": null, "vcodec": "none", "filesize": 1169842, "height": null, "ext": "m4a"}, {"tbr": 113.232, "abr": 113.232, "format_id": "251", "format": "251 - audio only (tiny)", "acodec": "opus", "container": "webm_dash", "asr": 48000, "quality": 0, "fps": null, "http_headers": {"Accept-Charset": "ISO-8859-1,utf-8;q=0.7,*;q=0.7", "Accept-Language": "en-us,en;q=0.5", "User-Agent": "Mozilla/5.0 (Windows NT 10.0; Win64; x64) AppleWebKit/537.36 (KHTML, like Gecko) Chrome/73.0.3683.112 Safari/537.36", "Accept": "text/html,application/xhtml+xml,application/xml;q=0.9,*/*;q=0.8", "Accept-Encoding": "gzip, deflate"}, "protocol": "https", "url": "https://r1---sn-vuxbavcx-5uiee.googlevideo.com/videoplayback?expire=1638295021&ei=jRGmYYLMLpOa-gb_uZeYBA&ip=79.129.41.108&id=o-ALrcOYgiOnLo48mGoquBYgezOis_kAvQ_cLt-BIQZolS&itag=251&source=youtube&requiressl=yes&mh=ep&mm=31%2C29&mn=sn-vuxbavcx-5uiee%2Csn-4g5lzner&ms=au%2Crdu&mv=m&mvi=1&pl=20&initcwndbps=862500&vprv=1&mime=audio%2Fwebm&ns=rfFp7bEHiA6Hm8WDTF3ULtUG&gir=yes&clen=2776201&otfp=1&dur=196.141&lmt=1563767633508796&mt=1638272935&fvip=1&keepalive=yes&fexp=24001373%2C24007246&c=WEB&n=gs6q7zgIbLYKMeck&sparams=expire%2Cei%2Cip%2Cid%2Citag%2Csource%2Crequiressl%2Cvprv%2Cmime%2Cns%2Cgir%2Cclen%2Cotfp%2Cdur%2Clmt&sig=AOq0QJ8wRAIgPLbBfvT0yZqKu4-gK8uCXjbKMCoMWOxKVxu69ywA1R4CIDxmdzo3YJ-tA6d5zxLMHGIb6Kdi3MwxrOwyC4m49pKp&lsparams=mh%2Cmm%2Cmn%2Cms%2Cmv%2Cmvi%2Cpl%2Cinitcwndbps&lsig=AG3C_xAwRQIgSwq_KAypJVpqeKGTqprQo0e0dw80SS4Jd7Jp0ykmxEsCIQD7L18OwAhQUzTkpcSoaj5PRVDrPiPG6pzp39zeQ6VZgw%3D%3D", "format_note": "tiny", "filesize": 2776201, "downloader_options": {"http_chunk_size": 10485760}, "vcodec": "none", "width": null, "height": null, "ext": "webm"}, {"tbr": 127.181, "abr": 127.181, "format_id": "140", "format": "140 - audio only (tiny)", "acodec": "mp4a.40.2", "container": "m4a_dash", "asr": 44100, "quality": 0, "fps": null, "http_headers": {"Accept-Charset": "ISO-8859-1,utf-8;q=0.7,*;q=0.7", "Accept-Language": "en-us,en;q=0.5", "User-Agent": "Mozilla/5.0 (Windows NT 10.0; Win64; x64) AppleWebKit/537.36 (KHTML, like Gecko) Chrome/73.0.3683.112 Safari/537.36", "Accept": "text/html,application/xhtml+xml,application/xml;q=0.9,*/*;q=0.8", "Accept-Encoding": "gzip, deflate"}, "protocol": "https", "url": "https://r1---sn-vuxbavcx-5uiee.googlevideo.com/videoplayback?expire=1638295021&ei=jRGmYYLMLpOa-gb_uZeYBA&ip=79.129.41.108&id=o-ALrcOYgiOnLo48mGoquBYgezOis_kAvQ_cLt-BIQZolS&itag=140&source=youtube&requiressl=yes&mh=ep&mm=31%2C29&mn=sn-vuxbavcx-5uiee%2Csn-4g5lzner&ms=au%2Crdu&mv=m&mvi=1&pl=20&initcwndbps=862500&vprv=1&mime=audio%2Fmp4&ns=rfFp7bEHiA6Hm8WDTF3ULtUG&gir=yes&clen=3117777&otfp=1&dur=196.115&lmt=1528053172189566&mt=1638272935&fvip=1&keepalive=yes&fexp=24001373%2C24007246&c=WEB&n=gs6q7zgIbLYKMeck&sparams=expire%2Cei%2Cip%2Cid%2Citag%2Csource%2Crequiressl%2Cvprv%2Cmime%2Cns%2Cgir%2Cclen%2Cotfp%2Cdur%2Clmt&sig=AOq0QJ8wRQIgQMwBEkmPyM0cF-9UiUIpgHsEhn_bhGPzZJBsEk6UB7wCIQC7dvsOZKCORa3bZ6QYJ7U9tHX0t6EU3VJM4dcULeTURQ%3D%3D&lsparams=mh%2Cmm%2Cmn%2Cms%2Cmv%2Cmvi%2Cpl%2Cinitcwndbps&lsig=AG3C_xAwRQIgSwq_KAypJVpqeKGTqprQo0e0dw80SS4Jd7Jp0ykmxEsCIQD7L18OwAhQUzTkpcSoaj5PRVDrPiPG6pzp39zeQ6VZgw%3D%3D", "format_note": "tiny", "filesize": 3117777, "downloader_options": {"http_chunk_size": 10485760}, "vcodec": "none", "width": null, "height": null, "ext": "m4a"}, {"tbr": 95.0, "container": "webm_dash", "format_id": "278", "http_headers": {"Accept-Charset": "ISO-8859-1,utf-8;q=0.7,*;q=0.7", "Accept-Language": "en-us,en;q=0.5", "User-Agent": "Mozilla/5.0 (Windows NT 10.0; Win64; x64) AppleWebKit/537.36 (KHTML, like Gecko) Chrome/73.0.3683.112 Safari/537.36", "Accept": "text/html,application/xhtml+xml,application/xml;q=0.9,*/*;q=0.8", "Accept-Encoding": "gzip, deflate"}, "acodec": "none", "format": "278 - 256x144 (DASH video)", "asr": null, "fragments": [{"path": "sq/0"}, {"duration": 5.339, "path": "sq/1/dur/5.339"}, {"duration": 5.338, "path": "sq/2/dur/5.338"}, {"duration": 5.339, "path": "sq/3/dur/5.339"}, {"duration": 5.339, "path": "sq/4/dur/5.339"}, {"duration": 5.338, "path": "sq/5/dur/5.338"}, {"duration": 5.339, "path": "sq/6/dur/5.339"}, {"duration": 5.339, "path": "sq/7/dur/5.339"}, {"duration": 5.338, "path": "sq/8/dur/5.338"}, {"duration": 5.339, "path": "sq/9/dur/5.339"}, {"duration": 5.339, "path": "sq/10/dur/5.339"}, {"duration": 5.338, "path": "sq/11/dur/5.338"}, {"duration": 5.339, "path": "sq/12/dur/5.339"}, {"duration": 5.339, "path": "sq/13/dur/5.339"}, {"duration": 5.338, "path": "sq/14/dur/5.338"}, {"duration": 5.339, "path": "sq/15/dur/5.339"}, {"duration": 5.339, "path": "sq/16/dur/5.339"}, {"duration": 5.338, "path": "sq/17/dur/5.338"}, {"duration": 5.339, "path": "sq/18/dur/5.339"}, {"duration": 5.339, "path": "sq/19/dur/5.339"}, {"duration": 5.338, "path": "sq/20/dur/5.338"}, {"duration": 5.339, "path": "sq/21/dur/5.339"}, {"duration": 5.339, "path": "sq/22/dur/5.339"}, {"duration": 5.338, "path": "sq/23/dur/5.338"}, {"duration": 5.339, "path": "sq/24/dur/5.339"}, {"duration": 5.339, "path": "sq/25/dur/5.339"}, {"duration": 5.338, "path": "sq/26/dur/5.338"}, {"duration": 5.339, "path": "sq/27/dur/5.339"}, {"duration": 5.339, "path": "sq/28/dur/5.339"}, {"duration": 5.338, "path": "sq/29/dur/5.338"}, {"duration": 5.339, "path": "sq/30/dur/5.339"}, {"duration": 5.339, "path": "sq/31/dur/5.339"}, {"duration": 5.338, "path": "sq/32/dur/5.338"}, {"duration": 5.339, "path": "sq/33/dur/5.339"}, {"duration": 5.339, "path": "sq/34/dur/5.339"}, {"duration": 5.338, "path": "sq/35/dur/5.338"}, {"duration": 5.339, "path": "sq/36/dur/5.339"}, {"duration": 3.871, "path": "sq/37/dur/3.871"}], "manifest_url": "https://manifest.googlevideo.com/api/manifest/dash/expire/1638295021/ei/jRGmYYLMLpOa-gb_uZeYBA/ip/79.129.41.108/id/c66eeb064d77ed9a/source/youtube/requiressl/yes/playback_host/r1---sn-vuxbavcx-5uiee.googlevideo.com/mh/ep/mm/31%2C29/mn/sn-vuxbavcx-5uiee%2Csn-4g5lzner/ms/au%2Crdu/mv/m/mvi/1/pl/20/hfr/all/as/fmp4_audio_clear%2Cwebm_audio_clear%2Cwebm2_audio_clear%2Cfmp4_sd_hd_clear%2Cwebm2_sd_hd_clear/initcwndbps/862500/vprv/1/mt/1638272935/fvip/1/keepalive/yes/fexp/24001373%2C24007246/itag/0/sparams/expire%2Cei%2Cip%2Cid%2Csource%2Crequiressl%2Chfr%2Cas%2Cvprv%2Citag/sig/AOq0QJ8wRQIgBg5L9VNZgI-V1InavELG4dBggS-g10tUMx1DQA9MLhoCIQDnMQDQFjMdXV0sQNk395Y-wTQBU6PwCdQ7ioIy67Hhxg%3D%3D/lsparams/playback_host%2Cmh%2Cmm%2Cmn%2Cms%2Cmv%2Cmvi%2Cpl%2Cinitcwndbps/lsig/AG3C_xAwRQIgbKLa6yYrXhf_Rsup11R-BBJjVSJfUFkqzM62MEGu-rkCIQCg97PRBxRiiLfZrhscwKF7QLpNMFt7R3bo4JUPjGtAXg%3D%3D", "quality": 0, "fps": 30, "protocol": "http_dash_segments", "url": "https://manifest.googlevideo.com/api/manifest/dash/expire/1638295021/ei/jRGmYYLMLpOa-gb_uZeYBA/ip/79.129.41.108/id/c66eeb064d77ed9a/source/youtube/requiressl/yes/playback_host/r1---sn-vuxbavcx-5uiee.googlevideo.com/mh/ep/mm/31%2C29/mn/sn-vuxbavcx-5uiee%2Csn-4g5lzner/ms/au%2Crdu/mv/m/mvi/1/pl/20/hfr/all/as/fmp4_audio_clear%2Cwebm_audio_clear%2Cwebm2_audio_clear%2Cfmp4_sd_hd_clear%2Cwebm2_sd_hd_clear/initcwndbps/862500/vprv/1/mt/1638272935/fvip/1/keepalive/yes/fexp/24001373%2C24007246/itag/0/sparams/expire%2Cei%2Cip%2Cid%2Csource%2Crequiressl%2Chfr%2Cas%2Cvprv%2Citag/sig/AOq0QJ8wRQIgBg5L9VNZgI-V1InavELG4dBggS-g10tUMx1DQA9MLhoCIQDnMQDQFjMdXV0sQNk395Y-wTQBU6PwCdQ7ioIy67Hhxg%3D%3D/lsparams/playback_host%2Cmh%2Cmm%2Cmn%2Cms%2Cmv%2Cmvi%2Cpl%2Cinitcwndbps/lsig/AG3C_xAwRQIgbKLa6yYrXhf_Rsup11R-BBJjVSJfUFkqzM62MEGu-rkCIQCg97PRBxRiiLfZrhscwKF7QLpNMFt7R3bo4JUPjGtAXg%3D%3D", "format_note": "DASH video", "fragment_base_url": "https://r1---sn-vuxbavcx-5uiee.googlevideo.com/videoplayback/expire/1638295021/ei/jRGmYYLMLpOa-gb_uZeYBA/ip/79.129.41.108/id/c66eeb064d77ed9a/itag/278/source/yt_otf/requiressl/yes/mh/ep/mm/31,29/mn/sn-vuxbavcx-5uiee,sn-4g5lzner/ms/au,rdu/mv/m/mvi/1/pl/20/initcwndbps/862500/vprv/1/ratebypass/yes/mime/video%2Fwebm/otfp/1/otf/1/lmt/1602059714097168/mt/1638272935/fvip/1/keepalive/yes/fexp/24001373,24007246/sparams/expire,ei,ip,id,itag,source,requiressl,vprv,ratebypass,mime,otfp,otf,lmt/sig/AOq0QJ8wRgIhAKEY_HIuMmBkaAjqmNd_CG11U9eo__pQ1M3sYGEkRYzIAiEAyK46hdnd7gpGgQV-rVFQGPsMuP9GtwDtz3eJ8CW9JoA%3D/lsparams/mh,mm,mn,ms,mv,mvi,pl,initcwndbps/lsig/AG3C_xAwRQIgLO7bvPd8DDqRaZJr3R6y_x-I_F9Rd9UcrhstrCDU7Y4CIQDq1fNDJp92y318OxuvQEd0sEvKYzDBNSs5oOKBmDE7UA%3D%3D/", "width": 256, "language": null, "vcodec": "vp9", "filesize": null, "height": 144, "ext": "webm"}, {"tbr": 108.0, "container": "mp4_dash", "format_id": "160", "http_headers": {"Accept-Charset": "ISO-8859-1,utf-8;q=0.7,*;q=0.7", "Accept-Language": "en-us,en;q=0.5", "User-Agent": "Mozilla/5.0 (Windows NT 10.0; Win64; x64) AppleWebKit/537.36 (KHTML, like Gecko) Chrome/73.0.3683.112 Safari/537.36", "Accept": "text/html,application/xhtml+xml,application/xml;q=0.9,*/*;q=0.8", "Accept-Encoding": "gzip, deflate"}, "acodec": "none", "format": "160 - 256x144 (DASH video)", "asr": null, "fragments": [{"path": "sq/0"}, {"duration": 5.339, "path": "sq/1/dur/5.339"}, {"duration": 5.338, "path": "sq/2/dur/5.338"}, {"duration": 5.339, "path": "sq/3/dur/5.339"}, {"duration": 5.339, "path": "sq/4/dur/5.339"}, {"duration": 5.338, "path": "sq/5/dur/5.338"}, {"duration": 5.339, "path": "sq/6/dur/5.339"}, {"duration": 5.339, "path": "sq/7/dur/5.339"}, {"duration": 5.338, "path": "sq/8/dur/5.338"}, {"duration": 5.339, "path": "sq/9/dur/5.339"}, {"duration": 5.339, "path": "sq/10/dur/5.339"}, {"duration": 5.338, "path": "sq/11/dur/5.338"}, {"duration": 5.339, "path": "sq/12/dur/5.339"}, {"duration": 5.339, "path": "sq/13/dur/5.339"}, {"duration": 5.338, "path": "sq/14/dur/5.338"}, {"duration": 5.339, "path": "sq/15/dur/5.339"}, {"duration": 5.339, "path": "sq/16/dur/5.339"}, {"duration": 5.338, "path": "sq/17/dur/5.338"}, {"duration": 5.339, "path": "sq/18/dur/5.339"}, {"duration": 5.339, "path": "sq/19/dur/5.339"}, {"duration": 5.338, "path": "sq/20/dur/5.338"}, {"duration": 5.339, "path": "sq/21/dur/5.339"}, {"duration": 5.339, "path": "sq/22/dur/5.339"}, {"duration": 5.338, "path": "sq/23/dur/5.338"}, {"duration": 5.339, "path": "sq/24/dur/5.339"}, {"duration": 5.339, "path": "sq/25/dur/5.339"}, {"duration": 5.338, "path": "sq/26/dur/5.338"}, {"duration": 5.339, "path": "sq/27/dur/5.339"}, {"duration": 5.339, "path": "sq/28/dur/5.339"}, {"duration": 5.338, "path": "sq/29/dur/5.338"}, {"duration": 5.339, "path": "sq/30/dur/5.339"}, {"duration": 5.339, "path": "sq/31/dur/5.339"}, {"duration": 5.338, "path": "sq/32/dur/5.338"}, {"duration": 5.339, "path": "sq/33/dur/5.339"}, {"duration": 5.339, "path": "sq/34/dur/5.339"}, {"duration": 5.338, "path": "sq/35/dur/5.338"}, {"duration": 5.339, "path": "sq/36/dur/5.339"}, {"duration": 3.871, "path": "sq/37/dur/3.871"}], "manifest_url": "https://manifest.googlevideo.com/api/manifest/dash/expire/1638295021/ei/jRGmYYLMLpOa-gb_uZeYBA/ip/79.129.41.108/id/c66eeb064d77ed9a/source/youtube/requiressl/yes/playback_host/r1---sn-vuxbavcx-5uiee.googlevideo.com/mh/ep/mm/31%2C29/mn/sn-vuxbavcx-5uiee%2Csn-4g5lzner/ms/au%2Crdu/mv/m/mvi/1/pl/20/hfr/all/as/fmp4_audio_clear%2Cwebm_audio_clear%2Cwebm2_audio_clear%2Cfmp4_sd_hd_clear%2Cwebm2_sd_hd_clear/initcwndbps/862500/vprv/1/mt/1638272935/fvip/1/keepalive/yes/fexp/24001373%2C24007246/itag/0/sparams/expire%2Cei%2Cip%2Cid%2Csource%2Crequiressl%2Chfr%2Cas%2Cvprv%2Citag/sig/AOq0QJ8wRQIgBg5L9VNZgI-V1InavELG4dBggS-g10tUMx1DQA9MLhoCIQDnMQDQFjMdXV0sQNk395Y-wTQBU6PwCdQ7ioIy67Hhxg%3D%3D/lsparams/playback_host%2Cmh%2Cmm%2Cmn%2Cms%2Cmv%2Cmvi%2Cpl%2Cinitcwndbps/lsig/AG3C_xAwRQIgbKLa6yYrXhf_Rsup11R-BBJjVSJfUFkqzM62MEGu-rkCIQCg97PRBxRiiLfZrhscwKF7QLpNMFt7R3bo4JUPjGtAXg%3D%3D", "quality": 0, "fps": 30, "protocol": "http_dash_segments", "url": "https://manifest.googlevideo.com/api/manifest/dash/expire/1638295021/ei/jRGmYYLMLpOa-gb_uZeYBA/ip/79.129.41.108/id/c66eeb064d77ed9a/source/youtube/requiressl/yes/playback_host/r1---sn-vuxbavcx-5uiee.googlevideo.com/mh/ep/mm/31%2C29/mn/sn-vuxbavcx-5uiee%2Csn-4g5lzner/ms/au%2Crdu/mv/m/mvi/1/pl/20/hfr/all/as/fmp4_audio_clear%2Cwebm_audio_clear%2Cwebm2_audio_clear%2Cfmp4_sd_hd_clear%2Cwebm2_sd_hd_clear/initcwndbps/862500/vprv/1/mt/1638272935/fvip/1/keepalive/yes/fexp/24001373%2C24007246/itag/0/sparams/expire%2Cei%2Cip%2Cid%2Csource%2Crequiressl%2Chfr%2Cas%2Cvprv%2Citag/sig/AOq0QJ8wRQIgBg5L9VNZgI-V1InavELG4dBggS-g10tUMx1DQA9MLhoCIQDnMQDQFjMdXV0sQNk395Y-wTQBU6PwCdQ7ioIy67Hhxg%3D%3D/lsparams/playback_host%2Cmh%2Cmm%2Cmn%2Cms%2Cmv%2Cmvi%2Cpl%2Cinitcwndbps/lsig/AG3C_xAwRQIgbKLa6yYrXhf_Rsup11R-BBJjVSJfUFkqzM62MEGu-rkCIQCg97PRBxRiiLfZrhscwKF7QLpNMFt7R3bo4JUPjGtAXg%3D%3D", "format_note": "DASH video", "fragment_base_url": "https://r1---sn-vuxbavcx-5uiee.googlevideo.com/videoplayback/expire/1638295021/ei/jRGmYYLMLpOa-gb_uZeYBA/ip/79.129.41.108/id/c66eeb064d77ed9a/itag/160/source/yt_otf/requiressl/yes/mh/ep/mm/31,29/mn/sn-vuxbavcx-5uiee,sn-4g5lzner/ms/au,rdu/mv/m/mvi/1/pl/20/initcwndbps/862500/vprv/1/ratebypass/yes/mime/video%2Fmp4/otfp/1/otf/1/lmt/1602059714097168/mt/1638272935/fvip/1/keepalive/yes/fexp/24001373,24007246/sparams/expire,ei,ip,id,itag,source,requiressl,vprv,ratebypass,mime,otfp,otf,lmt/sig/AOq0QJ8wRgIhAPlFo2vH2BGO8qhEFeWbGj5NgdMBonsBLpCT1ikI8K5wAiEAkBgBD_nzpoNDAu_Kr-5q8BezyGm9KKS0-jX3J4VHGv8%3D/lsparams/mh,mm,mn,ms,mv,mvi,pl,initcwndbps/lsig/AG3C_xAwRQIgHRJkGYoinGdgLlhMxRwcHgTxenhT0A00bAmVJ2E4op0CIQDepbYblFVA-4gsRaYL0GN-6Gd6u3dd9FeQsrPlWbx1Tw%3D%3D/", "width": 256, "language": null, "vcodec": "avc1.4d400b", "filesize": null, "height": 144, "ext": "mp4"}, {"tbr": 220.5, "container": "webm_dash", "format_id": "242", "http_headers": {"Accept-Charset": "ISO-8859-1,utf-8;q=0.7,*;q=0.7", "Accept-Language": "en-us,en;q=0.5", "User-Agent": "Mozilla/5.0 (Windows NT 10.0; Win64; x64) AppleWebKit/537.36 (KHTML, like Gecko) Chrome/73.0.3683.112 Safari/537.36", "Accept": "text/html,application/xhtml+xml,application/xml;q=0.9,*/*;q=0.8", "Accept-Encoding": "gzip, deflate"}, "acodec": "none", "format": "242 - 426x240 (DASH video)", "asr": null, "fragments": [{"path": "sq/0"}, {"duration": 5.339, "path": "sq/1/dur/5.339"}, {"duration": 5.338, "path": "sq/2/dur/5.338"}, {"duration": 5.339, "path": "sq/3/dur/5.339"}, {"duration": 5.339, "path": "sq/4/dur/5.339"}, {"duration": 5.338, "path": "sq/5/dur/5.338"}, {"duration": 5.339, "path": "sq/6/dur/5.339"}, {"duration": 5.339, "path": "sq/7/dur/5.339"}, {"duration": 5.338, "path": "sq/8/dur/5.338"}, {"duration": 5.339, "path": "sq/9/dur/5.339"}, {"duration": 5.339, "path": "sq/10/dur/5.339"}, {"duration": 5.338, "path": "sq/11/dur/5.338"}, {"duration": 5.339, "path": "sq/12/dur/5.339"}, {"duration": 5.339, "path": "sq/13/dur/5.339"}, {"duration": 5.338, "path": "sq/14/dur/5.338"}, {"duration": 5.339, "path": "sq/15/dur/5.339"}, {"duration": 5.339, "path": "sq/16/dur/5.339"}, {"duration": 5.338, "path": "sq/17/dur/5.338"}, {"duration": 5.339, "path": "sq/18/dur/5.339"}, {"duration": 5.339, "path": "sq/19/dur/5.339"}, {"duration": 5.338, "path": "sq/20/dur/5.338"}, {"duration": 5.339, "path": "sq/21/dur/5.339"}, {"duration": 5.339, "path": "sq/22/dur/5.339"}, {"duration": 5.338, "path": "sq/23/dur/5.338"}, {"duration": 5.339, "path": "sq/24/dur/5.339"}, {"duration": 5.339, "path": "sq/25/dur/5.339"}, {"duration": 5.338, "path": "sq/26/dur/5.338"}, {"duration": 5.339, "path": "sq/27/dur/5.339"}, {"duration": 5.339, "path": "sq/28/dur/5.339"}, {"duration": 5.338, "path": "sq/29/dur/5.338"}, {"duration": 5.339, "path": "sq/30/dur/5.339"}, {"duration": 5.339, "path": "sq/31/dur/5.339"}, {"duration": 5.338, "path": "sq/32/dur/5.338"}, {"duration": 5.339, "path": "sq/33/dur/5.339"}, {"duration": 5.339, "path": "sq/34/dur/5.339"}, {"duration": 5.338, "path": "sq/35/dur/5.338"}, {"duration": 5.339, "path": "sq/36/dur/5.339"}, {"duration": 3.871, "path": "sq/37/dur/3.871"}], "manifest_url": "https://manifest.googlevideo.com/api/manifest/dash/expire/1638295021/ei/jRGmYYLMLpOa-gb_uZeYBA/ip/79.129.41.108/id/c66eeb064d77ed9a/source/youtube/requiressl/yes/playback_host/r1---sn-vuxbavcx-5uiee.googlevideo.com/mh/ep/mm/31%2C29/mn/sn-vuxbavcx-5uiee%2Csn-4g5lzner/ms/au%2Crdu/mv/m/mvi/1/pl/20/hfr/all/as/fmp4_audio_clear%2Cwebm_audio_clear%2Cwebm2_audio_clear%2Cfmp4_sd_hd_clear%2Cwebm2_sd_hd_clear/initcwndbps/862500/vprv/1/mt/1638272935/fvip/1/keepalive/yes/fexp/24001373%2C24007246/itag/0/sparams/expire%2Cei%2Cip%2Cid%2Csource%2Crequiressl%2Chfr%2Cas%2Cvprv%2Citag/sig/AOq0QJ8wRQIgBg5L9VNZgI-V1InavELG4dBggS-g10tUMx1DQA9MLhoCIQDnMQDQFjMdXV0sQNk395Y-wTQBU6PwCdQ7ioIy67Hhxg%3D%3D/lsparams/playback_host%2Cmh%2Cmm%2Cmn%2Cms%2Cmv%2Cmvi%2Cpl%2Cinitcwndbps/lsig/AG3C_xAwRQIgbKLa6yYrXhf_Rsup11R-BBJjVSJfUFkqzM62MEGu-rkCIQCg97PRBxRiiLfZrhscwKF7QLpNMFt7R3bo4JUPjGtAXg%3D%3D", "quality": 1, "fps": 30, "protocol": "http_dash_segments", "url": "https://manifest.googlevideo.com/api/manifest/dash/expire/1638295021/ei/jRGmYYLMLpOa-gb_uZeYBA/ip/79.129.41.108/id/c66eeb064d77ed9a/source/youtube/requiressl/yes/playback_host/r1---sn-vuxbavcx-5uiee.googlevideo.com/mh/ep/mm/31%2C29/mn/sn-vuxbavcx-5uiee%2Csn-4g5lzner/ms/au%2Crdu/mv/m/mvi/1/pl/20/hfr/all/as/fmp4_audio_clear%2Cwebm_audio_clear%2Cwebm2_audio_clear%2Cfmp4_sd_hd_clear%2Cwebm2_sd_hd_clear/initcwndbps/862500/vprv/1/mt/1638272935/fvip/1/keepalive/yes/fexp/24001373%2C24007246/itag/0/sparams/expire%2Cei%2Cip%2Cid%2Csource%2Crequiressl%2Chfr%2Cas%2Cvprv%2Citag/sig/AOq0QJ8wRQIgBg5L9VNZgI-V1InavELG4dBggS-g10tUMx1DQA9MLhoCIQDnMQDQFjMdXV0sQNk395Y-wTQBU6PwCdQ7ioIy67Hhxg%3D%3D/lsparams/playback_host%2Cmh%2Cmm%2Cmn%2Cms%2Cmv%2Cmvi%2Cpl%2Cinitcwndbps/lsig/AG3C_xAwRQIgbKLa6yYrXhf_Rsup11R-BBJjVSJfUFkqzM62MEGu-rkCIQCg97PRBxRiiLfZrhscwKF7QLpNMFt7R3bo4JUPjGtAXg%3D%3D", "format_note": "DASH video", "fragment_base_url": "https://r1---sn-vuxbavcx-5uiee.googlevideo.com/videoplayback/expire/1638295021/ei/jRGmYYLMLpOa-gb_uZeYBA/ip/79.129.41.108/id/c66eeb064d77ed9a/itag/242/source/yt_otf/requiressl/yes/mh/ep/mm/31,29/mn/sn-vuxbavcx-5uiee,sn-4g5lzner/ms/au,rdu/mv/m/mvi/1/pl/20/initcwndbps/862500/vprv/1/ratebypass/yes/mime/video%2Fwebm/otfp/1/otf/1/lmt/1602059714097168/mt/1638272935/fvip/1/keepalive/yes/fexp/24001373,24007246/sparams/expire,ei,ip,id,itag,source,requiressl,vprv,ratebypass,mime,otfp,otf,lmt/sig/AOq0QJ8wRAIgCs1o-duNtjZVF-0PbC-u-dmKSEiGa0yqWWzyp_iBToICIHm4v4QtqIsMdA_telJsGlia3iPaFB_0GY7Rv3Nxd9We/lsparams/mh,mm,mn,ms,mv,mvi,pl,initcwndbps/lsig/AG3C_xAwRQIgM5BECQdIfq3dbdZQ0pMl-kXdIU_kMY6mW8zOyAg7IVECIQCpwO4IjEu2nQGiHizTWseyw47feeZ3kOulDFDyfU4Kgg%3D%3D/", "width": 426, "language": null, "vcodec": "vp9", "filesize": null, "height": 240, "ext": "webm"}, {"tbr": 242.0, "container": "mp4_dash", "format_id": "133", "http_headers": {"Accept-Charset": "ISO-8859-1,utf-8;q=0.7,*;q=0.7", "Accept-Language": "en-us,en;q=0.5", "User-Agent": "Mozilla/5.0 (Windows NT 10.0; Win64; x64) AppleWebKit/537.36 (KHTML, like Gecko) Chrome/73.0.3683.112 Safari/537.36", "Accept": "text/html,application/xhtml+xml,application/xml;q=0.9,*/*;q=0.8", "Accept-Encoding": "gzip, deflate"}, "acodec": "none", "format": "133 - 426x240 (DASH video)", "asr": null, "fragments": [{"path": "sq/0"}, {"duration": 5.339, "path": "sq/1/dur/5.339"}, {"duration": 5.338, "path": "sq/2/dur/5.338"}, {"duration": 5.339, "path": "sq/3/dur/5.339"}, {"duration": 5.339, "path": "sq/4/dur/5.339"}, {"duration": 5.338, "path": "sq/5/dur/5.338"}, {"duration": 5.339, "path": "sq/6/dur/5.339"}, {"duration": 5.339, "path": "sq/7/dur/5.339"}, {"duration": 5.338, "path": "sq/8/dur/5.338"}, {"duration": 5.339, "path": "sq/9/dur/5.339"}, {"duration": 5.339, "path": "sq/10/dur/5.339"}, {"duration": 5.338, "path": "sq/11/dur/5.338"}, {"duration": 5.339, "path": "sq/12/dur/5.339"}, {"duration": 5.339, "path": "sq/13/dur/5.339"}, {"duration": 5.338, "path": "sq/14/dur/5.338"}, {"duration": 5.339, "path": "sq/15/dur/5.339"}, {"duration": 5.339, "path": "sq/16/dur/5.339"}, {"duration": 5.338, "path": "sq/17/dur/5.338"}, {"duration": 5.339, "path": "sq/18/dur/5.339"}, {"duration": 5.339, "path": "sq/19/dur/5.339"}, {"duration": 5.338, "path": "sq/20/dur/5.338"}, {"duration": 5.339, "path": "sq/21/dur/5.339"}, {"duration": 5.339, "path": "sq/22/dur/5.339"}, {"duration": 5.338, "path": "sq/23/dur/5.338"}, {"duration": 5.339, "path": "sq/24/dur/5.339"}, {"duration": 5.339, "path": "sq/25/dur/5.339"}, {"duration": 5.338, "path": "sq/26/dur/5.338"}, {"duration": 5.339, "path": "sq/27/dur/5.339"}, {"duration": 5.339, "path": "sq/28/dur/5.339"}, {"duration": 5.338, "path": "sq/29/dur/5.338"}, {"duration": 5.339, "path": "sq/30/dur/5.339"}, {"duration": 5.339, "path": "sq/31/dur/5.339"}, {"duration": 5.338, "path": "sq/32/dur/5.338"}, {"duration": 5.339, "path": "sq/33/dur/5.339"}, {"duration": 5.339, "path": "sq/34/dur/5.339"}, {"duration": 5.338, "path": "sq/35/dur/5.338"}, {"duration": 5.339, "path": "sq/36/dur/5.339"}, {"duration": 3.871, "path": "sq/37/dur/3.871"}], "manifest_url": "https://manifest.googlevideo.com/api/manifest/dash/expire/1638295021/ei/jRGmYYLMLpOa-gb_uZeYBA/ip/79.129.41.108/id/c66eeb064d77ed9a/source/youtube/requiressl/yes/playback_host/r1---sn-vuxbavcx-5uiee.googlevideo.com/mh/ep/mm/31%2C29/mn/sn-vuxbavcx-5uiee%2Csn-4g5lzner/ms/au%2Crdu/mv/m/mvi/1/pl/20/hfr/all/as/fmp4_audio_clear%2Cwebm_audio_clear%2Cwebm2_audio_clear%2Cfmp4_sd_hd_clear%2Cwebm2_sd_hd_clear/initcwndbps/862500/vprv/1/mt/1638272935/fvip/1/keepalive/yes/fexp/24001373%2C24007246/itag/0/sparams/expire%2Cei%2Cip%2Cid%2Csource%2Crequiressl%2Chfr%2Cas%2Cvprv%2Citag/sig/AOq0QJ8wRQIgBg5L9VNZgI-V1InavELG4dBggS-g10tUMx1DQA9MLhoCIQDnMQDQFjMdXV0sQNk395Y-wTQBU6PwCdQ7ioIy67Hhxg%3D%3D/lsparams/playback_host%2Cmh%2Cmm%2Cmn%2Cms%2Cmv%2Cmvi%2Cpl%2Cinitcwndbps/lsig/AG3C_xAwRQIgbKLa6yYrXhf_Rsup11R-BBJjVSJfUFkqzM62MEGu-rkCIQCg97PRBxRiiLfZrhscwKF7QLpNMFt7R3bo4JUPjGtAXg%3D%3D", "quality": 1, "fps": 30, "protocol": "http_dash_segments", "url": "https://manifest.googlevideo.com/api/manifest/dash/expire/1638295021/ei/jRGmYYLMLpOa-gb_uZeYBA/ip/79.129.41.108/id/c66eeb064d77ed9a/source/youtube/requiressl/yes/playback_host/r1---sn-vuxbavcx-5uiee.googlevideo.com/mh/ep/mm/31%2C29/mn/sn-vuxbavcx-5uiee%2Csn-4g5lzner/ms/au%2Crdu/mv/m/mvi/1/pl/20/hfr/all/as/fmp4_audio_clear%2Cwebm_audio_clear%2Cwebm2_audio_clear%2Cfmp4_sd_hd_clear%2Cwebm2_sd_hd_clear/initcwndbps/862500/vprv/1/mt/1638272935/fvip/1/keepalive/yes/fexp/24001373%2C24007246/itag/0/sparams/expire%2Cei%2Cip%2Cid%2Csource%2Crequiressl%2Chfr%2Cas%2Cvprv%2Citag/sig/AOq0QJ8wRQIgBg5L9VNZgI-V1InavELG4dBggS-g10tUMx1DQA9MLhoCIQDnMQDQFjMdXV0sQNk395Y-wTQBU6PwCdQ7ioIy67Hhxg%3D%3D/lsparams/playback_host%2Cmh%2Cmm%2Cmn%2Cms%2Cmv%2Cmvi%2Cpl%2Cinitcwndbps/lsig/AG3C_xAwRQIgbKLa6yYrXhf_Rsup11R-BBJjVSJfUFkqzM62MEGu-rkCIQCg97PRBxRiiLfZrhscwKF7QLpNMFt7R3bo4JUPjGtAXg%3D%3D", "format_note": "DASH video", "fragment_base_url": "https://r1---sn-vuxbavcx-5uiee.googlevideo.com/videoplayback/expire/1638295021/ei/jRGmYYLMLpOa-gb_uZeYBA/ip/79.129.41.108/id/c66eeb064d77ed9a/itag/133/source/yt_otf/requiressl/yes/mh/ep/mm/31,29/mn/sn-vuxbavcx-5uiee,sn-4g5lzner/ms/au,rdu/mv/m/mvi/1/pl/20/initcwndbps/862500/vprv/1/ratebypass/yes/mime/video%2Fmp4/otfp/1/otf/1/lmt/1602059714097168/mt/1638272935/fvip/1/keepalive/yes/fexp/24001373,24007246/sparams/expire,ei,ip,id,itag,source,requiressl,vprv,ratebypass,mime,otfp,otf,lmt/sig/AOq0QJ8wRgIhALHNPQ7cBEa8Vl1nU1zsFeWFcZ-SvFbA2OKt7sqRU4rtAiEA1vyQgsNSs1wUiMsgOHM29YC_2Hre5v6XFeiFSRQNDXo%3D/lsparams/mh,mm,mn,ms,mv,mvi,pl,initcwndbps/lsig/AG3C_xAwRgIhALQmYBXf5O5EfA9GZKjaqUbEs4FpFG0r6l5Ac861yIo0AiEAw68HfOx3aFRebYCB7HBr9d9IOhTgWzExpRFJAl9LXbI%3D/", "width": 426, "language": null, "vcodec": "avc1.4d400c", "filesize": null, "height": 240, "ext": "mp4"}, {"tbr": 376.026, "container": "mp4_dash", "format_id": "134", "http_headers": {"Accept-Charset": "ISO-8859-1,utf-8;q=0.7,*;q=0.7", "Accept-Language": "en-us,en;q=0.5", "User-Agent": "Mozilla/5.0 (Windows NT 10.0; Win64; x64) AppleWebKit/537.36 (KHTML, like Gecko) Chrome/73.0.3683.112 Safari/537.36", "Accept": "text/html,application/xhtml+xml,application/xml;q=0.9,*/*;q=0.8", "Accept-Encoding": "gzip, deflate"}, "acodec": "none", "format": "134 - 640x360 (360p)", "asr": null, "vbr": 376.026, "quality": 2, "fps": 30, "protocol": "https", "url": "https://r1---sn-vuxbavcx-5uiee.googlevideo.com/videoplayback?expire=1638295021&ei=jRGmYYLMLpOa-gb_uZeYBA&ip=79.129.41.108&id=o-ALrcOYgiOnLo48mGoquBYgezOis_kAvQ_cLt-BIQZolS&itag=134&aitags=133%2C134%2C135%2C136%2C137%2C160%2C242%2C243%2C244%2C247%2C248%2C278&source=youtube&requiressl=yes&mh=ep&mm=31%2C29&mn=sn-vuxbavcx-5uiee%2Csn-4g5lzner&ms=au%2Crdu&mv=m&mvi=1&pl=20&initcwndbps=862500&vprv=1&mime=video%2Fmp4&ns=rfFp7bEHiA6Hm8WDTF3ULtUG&gir=yes&clen=9215552&otfp=1&dur=196.062&lmt=1602059731201212&mt=1638272935&fvip=1&keepalive=yes&fexp=24001373%2C24007246&c=WEB&n=gs6q7zgIbLYKMeck&sparams=expire%2Cei%2Cip%2Cid%2Caitags%2Csource%2Crequiressl%2Cvprv%2Cmime%2Cns%2Cgir%2Cclen%2Cotfp%2Cdur%2Clmt&sig=AOq0QJ8wRQIhANGm39QpB640_Ce-PKmwV6-ox8x3OraQRhFGTtovyUmoAiBqx0dJS6GL2EHqgRMWzeuzqAtdhDzfsNvNmMU1yq36cA%3D%3D&lsparams=mh%2Cmm%2Cmn%2Cms%2Cmv%2Cmvi%2Cpl%2Cinitcwndbps&lsig=AG3C_xAwRQIgSwq_KAypJVpqeKGTqprQo0e0dw80SS4Jd7Jp0ykmxEsCIQD7L18OwAhQUzTkpcSoaj5PRVDrPiPG6pzp39zeQ6VZgw%3D%3D", "format_note": "360p", "filesize": 9215552, "downloader_options": {"http_chunk_size": 10485760}, "vcodec": "avc1.4d401e", "width": 640, "height": 360, "ext": "mp4"}, {"tbr": 405.72, "container": "webm_dash", "format_id": "243", "http_headers": {"Accept-Charset": "ISO-8859-1,utf-8;q=0.7,*;q=0.7", "Accept-Language": "en-us,en;q=0.5", "User-Agent": "Mozilla/5.0 (Windows NT 10.0; Win64; x64) AppleWebKit/537.36 (KHTML, like Gecko) Chrome/73.0.3683.112 Safari/537.36", "Accept": "text/html,application/xhtml+xml,application/xml;q=0.9,*/*;q=0.8", "Accept-Encoding": "gzip, deflate"}, "acodec": "none", "format": "243 - 640x360 (DASH video)", "asr": null, "fragments": [{"path": "sq/0"}, {"duration": 5.339, "path": "sq/1/dur/5.339"}, {"duration": 5.338, "path": "sq/2/dur/5.338"}, {"duration": 5.339, "path": "sq/3/dur/5.339"}, {"duration": 5.339, "path": "sq/4/dur/5.339"}, {"duration": 5.338, "path": "sq/5/dur/5.338"}, {"duration": 5.339, "path": "sq/6/dur/5.339"}, {"duration": 5.339, "path": "sq/7/dur/5.339"}, {"duration": 5.338, "path": "sq/8/dur/5.338"}, {"duration": 5.339, "path": "sq/9/dur/5.339"}, {"duration": 5.339, "path": "sq/10/dur/5.339"}, {"duration": 5.338, "path": "sq/11/dur/5.338"}, {"duration": 5.339, "path": "sq/12/dur/5.339"}, {"duration": 5.339, "path": "sq/13/dur/5.339"}, {"duration": 5.338, "path": "sq/14/dur/5.338"}, {"duration": 5.339, "path": "sq/15/dur/5.339"}, {"duration": 5.339, "path": "sq/16/dur/5.339"}, {"duration": 5.338, "path": "sq/17/dur/5.338"}, {"duration": 5.339, "path": "sq/18/dur/5.339"}, {"duration": 5.339, "path": "sq/19/dur/5.339"}, {"duration": 5.338, "path": "sq/20/dur/5.338"}, {"duration": 5.339, "path": "sq/21/dur/5.339"}, {"duration": 5.339, "path": "sq/22/dur/5.339"}, {"duration": 5.338, "path": "sq/23/dur/5.338"}, {"duration": 5.339, "path": "sq/24/dur/5.339"}, {"duration": 5.339, "path": "sq/25/dur/5.339"}, {"duration": 5.338, "path": "sq/26/dur/5.338"}, {"duration": 5.339, "path": "sq/27/dur/5.339"}, {"duration": 5.339, "path": "sq/28/dur/5.339"}, {"duration": 5.338, "path": "sq/29/dur/5.338"}, {"duration": 5.339, "path": "sq/30/dur/5.339"}, {"duration": 5.339, "path": "sq/31/dur/5.339"}, {"duration": 5.338, "path": "sq/32/dur/5.338"}, {"duration": 5.339, "path": "sq/33/dur/5.339"}, {"duration": 5.339, "path": "sq/34/dur/5.339"}, {"duration": 5.338, "path": "sq/35/dur/5.338"}, {"duration": 5.339, "path": "sq/36/dur/5.339"}, {"duration": 3.871, "path": "sq/37/dur/3.871"}], "manifest_url": "https://manifest.googlevideo.com/api/manifest/dash/expire/1638295021/ei/jRGmYYLMLpOa-gb_uZeYBA/ip/79.129.41.108/id/c66eeb064d77ed9a/source/youtube/requiressl/yes/playback_host/r1---sn-vuxbavcx-5uiee.googlevideo.com/mh/ep/mm/31%2C29/mn/sn-vuxbavcx-5uiee%2Csn-4g5lzner/ms/au%2Crdu/mv/m/mvi/1/pl/20/hfr/all/as/fmp4_audio_clear%2Cwebm_audio_clear%2Cwebm2_audio_clear%2Cfmp4_sd_hd_clear%2Cwebm2_sd_hd_clear/initcwndbps/862500/vprv/1/mt/1638272935/fvip/1/keepalive/yes/fexp/24001373%2C24007246/itag/0/sparams/expire%2Cei%2Cip%2Cid%2Csource%2Crequiressl%2Chfr%2Cas%2Cvprv%2Citag/sig/AOq0QJ8wRQIgBg5L9VNZgI-V1InavELG4dBggS-g10tUMx1DQA9MLhoCIQDnMQDQFjMdXV0sQNk395Y-wTQBU6PwCdQ7ioIy67Hhxg%3D%3D/lsparams/playback_host%2Cmh%2Cmm%2Cmn%2Cms%2Cmv%2Cmvi%2Cpl%2Cinitcwndbps/lsig/AG3C_xAwRQIgbKLa6yYrXhf_Rsup11R-BBJjVSJfUFkqzM62MEGu-rkCIQCg97PRBxRiiLfZrhscwKF7QLpNMFt7R3bo4JUPjGtAXg%3D%3D", "quality": 2, "fps": 30, "protocol": "http_dash_segments", "url": "https://manifest.googlevideo.com/api/manifest/dash/expire/1638295021/ei/jRGmYYLMLpOa-gb_uZeYBA/ip/79.129.41.108/id/c66eeb064d77ed9a/source/youtube/requiressl/yes/playback_host/r1---sn-vuxbavcx-5uiee.googlevideo.com/mh/ep/mm/31%2C29/mn/sn-vuxbavcx-5uiee%2Csn-4g5lzner/ms/au%2Crdu/mv/m/mvi/1/pl/20/hfr/all/as/fmp4_audio_clear%2Cwebm_audio_clear%2Cwebm2_audio_clear%2Cfmp4_sd_hd_clear%2Cwebm2_sd_hd_clear/initcwndbps/862500/vprv/1/mt/1638272935/fvip/1/keepalive/yes/fexp/24001373%2C24007246/itag/0/sparams/expire%2Cei%2Cip%2Cid%2Csource%2Crequiressl%2Chfr%2Cas%2Cvprv%2Citag/sig/AOq0QJ8wRQIgBg5L9VNZgI-V1InavELG4dBggS-g10tUMx1DQA9MLhoCIQDnMQDQFjMdXV0sQNk395Y-wTQBU6PwCdQ7ioIy67Hhxg%3D%3D/lsparams/playback_host%2Cmh%2Cmm%2Cmn%2Cms%2Cmv%2Cmvi%2Cpl%2Cinitcwndbps/lsig/AG3C_xAwRQIgbKLa6yYrXhf_Rsup11R-BBJjVSJfUFkqzM62MEGu-rkCIQCg97PRBxRiiLfZrhscwKF7QLpNMFt7R3bo4JUPjGtAXg%3D%3D", "format_note": "DASH video", "fragment_base_url": "https://r1---sn-vuxbavcx-5uiee.googlevideo.com/videoplayback/expire/1638295021/ei/jRGmYYLMLpOa-gb_uZeYBA/ip/79.129.41.108/id/c66eeb064d77ed9a/itag/243/source/yt_otf/requiressl/yes/mh/ep/mm/31,29/mn/sn-vuxbavcx-5uiee,sn-4g5lzner/ms/au,rdu/mv/m/mvi/1/pl/20/initcwndbps/862500/vprv/1/ratebypass/yes/mime/video%2Fwebm/otfp/1/otf/1/lmt/1602059714097168/mt/1638272935/fvip/1/keepalive/yes/fexp/24001373,24007246/sparams/expire,ei,ip,id,itag,source,requiressl,vprv,ratebypass,mime,otfp,otf,lmt/sig/AOq0QJ8wRQIgAnDt5IaHA4-0OdhIHNAm8sCB_fzp2qU1ZhtuhHle4rkCIQCa6kH8YZVUiYIU1SlRyzdR28oMNJ1Z2GrqNC0EkEYgAA%3D%3D/lsparams/mh,mm,mn,ms,mv,mvi,pl,initcwndbps/lsig/AG3C_xAwRAIgYLXfSiSwU7v26g-61rTUj2EBfHo8gTP40bD1En-5dd8CIB7PZ9TLlU3CMdErgxrLAT_6jvOk57rGnQtb5uxgNcGO/", "width": 640, "language": null, "vcodec": "vp9", "filesize": null, "height": 360, "ext": "webm"}, {"tbr": 752.64, "container": "webm_dash", "format_id": "244", "http_headers": {"Accept-Charset": "ISO-8859-1,utf-8;q=0.7,*;q=0.7", "Accept-Language": "en-us,en;q=0.5", "User-Agent": "Mozilla/5.0 (Windows NT 10.0; Win64; x64) AppleWebKit/537.36 (KHTML, like Gecko) Chrome/73.0.3683.112 Safari/537.36", "Accept": "text/html,application/xhtml+xml,application/xml;q=0.9,*/*;q=0.8", "Accept-Encoding": "gzip, deflate"}, "acodec": "none", "format": "244 - 854x480 (DASH video)", "asr": null, "fragments": [{"path": "sq/0"}, {"duration": 5.339, "path": "sq/1/dur/5.339"}, {"duration": 5.338, "path": "sq/2/dur/5.338"}, {"duration": 5.339, "path": "sq/3/dur/5.339"}, {"duration": 5.339, "path": "sq/4/dur/5.339"}, {"duration": 5.338, "path": "sq/5/dur/5.338"}, {"duration": 5.339, "path": "sq/6/dur/5.339"}, {"duration": 5.339, "path": "sq/7/dur/5.339"}, {"duration": 5.338, "path": "sq/8/dur/5.338"}, {"duration": 5.339, "path": "sq/9/dur/5.339"}, {"duration": 5.339, "path": "sq/10/dur/5.339"}, {"duration": 5.338, "path": "sq/11/dur/5.338"}, {"duration": 5.339, "path": "sq/12/dur/5.339"}, {"duration": 5.339, "path": "sq/13/dur/5.339"}, {"duration": 5.338, "path": "sq/14/dur/5.338"}, {"duration": 5.339, "path": "sq/15/dur/5.339"}, {"duration": 5.339, "path": "sq/16/dur/5.339"}, {"duration": 5.338, "path": "sq/17/dur/5.338"}, {"duration": 5.339, "path": "sq/18/dur/5.339"}, {"duration": 5.339, "path": "sq/19/dur/5.339"}, {"duration": 5.338, "path": "sq/20/dur/5.338"}, {"duration": 5.339, "path": "sq/21/dur/5.339"}, {"duration": 5.339, "path": "sq/22/dur/5.339"}, {"duration": 5.338, "path": "sq/23/dur/5.338"}, {"duration": 5.339, "path": "sq/24/dur/5.339"}, {"duration": 5.339, "path": "sq/25/dur/5.339"}, {"duration": 5.338, "path": "sq/26/dur/5.338"}, {"duration": 5.339, "path": "sq/27/dur/5.339"}, {"duration": 5.339, "path": "sq/28/dur/5.339"}, {"duration": 5.338, "path": "sq/29/dur/5.338"}, {"duration": 5.339, "path": "sq/30/dur/5.339"}, {"duration": 5.339, "path": "sq/31/dur/5.339"}, {"duration": 5.338, "path": "sq/32/dur/5.338"}, {"duration": 5.339, "path": "sq/33/dur/5.339"}, {"duration": 5.339, "path": "sq/34/dur/5.339"}, {"duration": 5.338, "path": "sq/35/dur/5.338"}, {"duration": 5.339, "path": "sq/36/dur/5.339"}, {"duration": 3.871, "path": "sq/37/dur/3.871"}], "manifest_url": "https://manifest.googlevideo.com/api/manifest/dash/expire/1638295021/ei/jRGmYYLMLpOa-gb_uZeYBA/ip/79.129.41.108/id/c66eeb064d77ed9a/source/youtube/requiressl/yes/playback_host/r1---sn-vuxbavcx-5uiee.googlevideo.com/mh/ep/mm/31%2C29/mn/sn-vuxbavcx-5uiee%2Csn-4g5lzner/ms/au%2Crdu/mv/m/mvi/1/pl/20/hfr/all/as/fmp4_audio_clear%2Cwebm_audio_clear%2Cwebm2_audio_clear%2Cfmp4_sd_hd_clear%2Cwebm2_sd_hd_clear/initcwndbps/862500/vprv/1/mt/1638272935/fvip/1/keepalive/yes/fexp/24001373%2C24007246/itag/0/sparams/expire%2Cei%2Cip%2Cid%2Csource%2Crequiressl%2Chfr%2Cas%2Cvprv%2Citag/sig/AOq0QJ8wRQIgBg5L9VNZgI-V1InavELG4dBggS-g10tUMx1DQA9MLhoCIQDnMQDQFjMdXV0sQNk395Y-wTQBU6PwCdQ7ioIy67Hhxg%3D%3D/lsparams/playback_host%2Cmh%2Cmm%2Cmn%2Cms%2Cmv%2Cmvi%2Cpl%2Cinitcwndbps/lsig/AG3C_xAwRQIgbKLa6yYrXhf_Rsup11R-BBJjVSJfUFkqzM62MEGu-rkCIQCg97PRBxRiiLfZrhscwKF7QLpNMFt7R3bo4JUPjGtAXg%3D%3D", "quality": 3, "fps": 30, "protocol": "http_dash_segments", "url": "https://manifest.googlevideo.com/api/manifest/dash/expire/1638295021/ei/jRGmYYLMLpOa-gb_uZeYBA/ip/79.129.41.108/id/c66eeb064d77ed9a/source/youtube/requiressl/yes/playback_host/r1---sn-vuxbavcx-5uiee.googlevideo.com/mh/ep/mm/31%2C29/mn/sn-vuxbavcx-5uiee%2Csn-4g5lzner/ms/au%2Crdu/mv/m/mvi/1/pl/20/hfr/all/as/fmp4_audio_clear%2Cwebm_audio_clear%2Cwebm2_audio_clear%2Cfmp4_sd_hd_clear%2Cwebm2_sd_hd_clear/initcwndbps/862500/vprv/1/mt/1638272935/fvip/1/keepalive/yes/fexp/24001373%2C24007246/itag/0/sparams/expire%2Cei%2Cip%2Cid%2Csource%2Crequiressl%2Chfr%2Cas%2Cvprv%2Citag/sig/AOq0QJ8wRQIgBg5L9VNZgI-V1InavELG4dBggS-g10tUMx1DQA9MLhoCIQDnMQDQFjMdXV0sQNk395Y-wTQBU6PwCdQ7ioIy67Hhxg%3D%3D/lsparams/playback_host%2Cmh%2Cmm%2Cmn%2Cms%2Cmv%2Cmvi%2Cpl%2Cinitcwndbps/lsig/AG3C_xAwRQIgbKLa6yYrXhf_Rsup11R-BBJjVSJfUFkqzM62MEGu-rkCIQCg97PRBxRiiLfZrhscwKF7QLpNMFt7R3bo4JUPjGtAXg%3D%3D", "format_note": "DASH video", "fragment_base_url": "https://r1---sn-vuxbavcx-5uiee.googlevideo.com/videoplayback/expire/1638295021/ei/jRGmYYLMLpOa-gb_uZeYBA/ip/79.129.41.108/id/c66eeb064d77ed9a/itag/244/source/yt_otf/requiressl/yes/mh/ep/mm/31,29/mn/sn-vuxbavcx-5uiee,sn-4g5lzner/ms/au,rdu/mv/m/mvi/1/pl/20/initcwndbps/862500/vprv/1/ratebypass/yes/mime/video%2Fwebm/otfp/1/otf/1/lmt/1602059714097168/mt/1638272935/fvip/1/keepalive/yes/fexp/24001373,24007246/sparams/expire,ei,ip,id,itag,source,requiressl,vprv,ratebypass,mime,otfp,otf,lmt/sig/AOq0QJ8wRQIgRV3ZgLADJJTanMjx4Z38UzgFgSBDgQQpF5_WY93u0PYCIQDgdQzu93Qd082lrRK7C_O1q0pJPK8n04OhkyQs1C4jIg%3D%3D/lsparams/mh,mm,mn,ms,mv,mvi,pl,initcwndbps/lsig/AG3C_xAwRgIhAOhieVMLoZlk3LiH-P8ZxF95PCLSIifnYKMkLjv-C7HFAiEAwsUkk2VFI82DT7O3FYOfYM-ePFgVxki3QWsvfZrysXo%3D/", "width": 854, "language": null, "vcodec": "vp9", "filesize": null, "height": 480, "ext": "webm"}, {"tbr": 1155.0, "container": "mp4_dash", "format_id": "135", "http_headers": {"Accept-Charset": "ISO-8859-1,utf-8;q=0.7,*;q=0.7", "Accept-Language": "en-us,en;q=0.5", "User-Agent": "Mozilla/5.0 (Windows NT 10.0; Win64; x64) AppleWebKit/537.36 (KHTML, like Gecko) Chrome/73.0.3683.112 Safari/537.36", "Accept": "text/html,application/xhtml+xml,application/xml;q=0.9,*/*;q=0.8", "Accept-Encoding": "gzip, deflate"}, "acodec": "none", "format": "135 - 854x480 (DASH video)", "asr": null, "fragments": [{"path": "sq/0"}, {"duration": 5.339, "path": "sq/1/dur/5.339"}, {"duration": 5.338, "path": "sq/2/dur/5.338"}, {"duration": 5.339, "path": "sq/3/dur/5.339"}, {"duration": 5.339, "path": "sq/4/dur/5.339"}, {"duration": 5.338, "path": "sq/5/dur/5.338"}, {"duration": 5.339, "path": "sq/6/dur/5.339"}, {"duration": 5.339, "path": "sq/7/dur/5.339"}, {"duration": 5.338, "path": "sq/8/dur/5.338"}, {"duration": 5.339, "path": "sq/9/dur/5.339"}, {"duration": 5.339, "path": "sq/10/dur/5.339"}, {"duration": 5.338, "path": "sq/11/dur/5.338"}, {"duration": 5.339, "path": "sq/12/dur/5.339"}, {"duration": 5.339, "path": "sq/13/dur/5.339"}, {"duration": 5.338, "path": "sq/14/dur/5.338"}, {"duration": 5.339, "path": "sq/15/dur/5.339"}, {"duration": 5.339, "path": "sq/16/dur/5.339"}, {"duration": 5.338, "path": "sq/17/dur/5.338"}, {"duration": 5.339, "path": "sq/18/dur/5.339"}, {"duration": 5.339, "path": "sq/19/dur/5.339"}, {"duration": 5.338, "path": "sq/20/dur/5.338"}, {"duration": 5.339, "path": "sq/21/dur/5.339"}, {"duration": 5.339, "path": "sq/22/dur/5.339"}, {"duration": 5.338, "path": "sq/23/dur/5.338"}, {"duration": 5.339, "path": "sq/24/dur/5.339"}, {"duration": 5.339, "path": "sq/25/dur/5.339"}, {"duration": 5.338, "path": "sq/26/dur/5.338"}, {"duration": 5.339, "path": "sq/27/dur/5.339"}, {"duration": 5.339, "path": "sq/28/dur/5.339"}, {"duration": 5.338, "path": "sq/29/dur/5.338"}, {"duration": 5.339, "path": "sq/30/dur/5.339"}, {"duration": 5.339, "path": "sq/31/dur/5.339"}, {"duration": 5.338, "path": "sq/32/dur/5.338"}, {"duration": 5.339, "path": "sq/33/dur/5.339"}, {"duration": 5.339, "path": "sq/34/dur/5.339"}, {"duration": 5.338, "path": "sq/35/dur/5.338"}, {"duration": 5.339, "path": "sq/36/dur/5.339"}, {"duration": 3.871, "path": "sq/37/dur/3.871"}], "manifest_url": "https://manifest.googlevideo.com/api/manifest/dash/expire/1638295021/ei/jRGmYYLMLpOa-gb_uZeYBA/ip/79.129.41.108/id/c66eeb064d77ed9a/source/youtube/requiressl/yes/playback_host/r1---sn-vuxbavcx-5uiee.googlevideo.com/mh/ep/mm/31%2C29/mn/sn-vuxbavcx-5uiee%2Csn-4g5lzner/ms/au%2Crdu/mv/m/mvi/1/pl/20/hfr/all/as/fmp4_audio_clear%2Cwebm_audio_clear%2Cwebm2_audio_clear%2Cfmp4_sd_hd_clear%2Cwebm2_sd_hd_clear/initcwndbps/862500/vprv/1/mt/1638272935/fvip/1/keepalive/yes/fexp/24001373%2C24007246/itag/0/sparams/expire%2Cei%2Cip%2Cid%2Csource%2Crequiressl%2Chfr%2Cas%2Cvprv%2Citag/sig/AOq0QJ8wRQIgBg5L9VNZgI-V1InavELG4dBggS-g10tUMx1DQA9MLhoCIQDnMQDQFjMdXV0sQNk395Y-wTQBU6PwCdQ7ioIy67Hhxg%3D%3D/lsparams/playback_host%2Cmh%2Cmm%2Cmn%2Cms%2Cmv%2Cmvi%2Cpl%2Cinitcwndbps/lsig/AG3C_xAwRQIgbKLa6yYrXhf_Rsup11R-BBJjVSJfUFkqzM62MEGu-rkCIQCg97PRBxRiiLfZrhscwKF7QLpNMFt7R3bo4JUPjGtAXg%3D%3D", "quality": 3, "fps": 30, "protocol": "http_dash_segments", "url": "https://manifest.googlevideo.com/api/manifest/dash/expire/1638295021/ei/jRGmYYLMLpOa-gb_uZeYBA/ip/79.129.41.108/id/c66eeb064d77ed9a/source/youtube/requiressl/yes/playback_host/r1---sn-vuxbavcx-5uiee.googlevideo.com/mh/ep/mm/31%2C29/mn/sn-vuxbavcx-5uiee%2Csn-4g5lzner/ms/au%2Crdu/mv/m/mvi/1/pl/20/hfr/all/as/fmp4_audio_clear%2Cwebm_audio_clear%2Cwebm2_audio_clear%2Cfmp4_sd_hd_clear%2Cwebm2_sd_hd_clear/initcwndbps/862500/vprv/1/mt/1638272935/fvip/1/keepalive/yes/fexp/24001373%2C24007246/itag/0/sparams/expire%2Cei%2Cip%2Cid%2Csource%2Crequiressl%2Chfr%2Cas%2Cvprv%2Citag/sig/AOq0QJ8wRQIgBg5L9VNZgI-V1InavELG4dBggS-g10tUMx1DQA9MLhoCIQDnMQDQFjMdXV0sQNk395Y-wTQBU6PwCdQ7ioIy67Hhxg%3D%3D/lsparams/playback_host%2Cmh%2Cmm%2Cmn%2Cms%2Cmv%2Cmvi%2Cpl%2Cinitcwndbps/lsig/AG3C_xAwRQIgbKLa6yYrXhf_Rsup11R-BBJjVSJfUFkqzM62MEGu-rkCIQCg97PRBxRiiLfZrhscwKF7QLpNMFt7R3bo4JUPjGtAXg%3D%3D", "format_note": "DASH video", "fragment_base_url": "https://r1---sn-vuxbavcx-5uiee.googlevideo.com/videoplayback/expire/1638295021/ei/jRGmYYLMLpOa-gb_uZeYBA/ip/79.129.41.108/id/c66eeb064d77ed9a/itag/135/source/yt_otf/requiressl/yes/mh/ep/mm/31,29/mn/sn-vuxbavcx-5uiee,sn-4g5lzner/ms/au,rdu/mv/m/mvi/1/pl/20/initcwndbps/862500/vprv/1/ratebypass/yes/mime/video%2Fmp4/otfp/1/otf/1/lmt/1602059714097168/mt/1638272935/fvip/1/keepalive/yes/fexp/24001373,24007246/sparams/expire,ei,ip,id,itag,source,requiressl,vprv,ratebypass,mime,otfp,otf,lmt/sig/AOq0QJ8wRgIhAP686dWp4ZvsZLJcw45LHxq_omq8rfUQ5OWPdkloAP-wAiEAx2xyCMztNXrQC06oNySHmm597fxkZS329qZMrBY_9Rk%3D/lsparams/mh,mm,mn,ms,mv,mvi,pl,initcwndbps/lsig/AG3C_xAwRQIgY4AHBhIWCqhwCYibIHAT5_TJGyar8YdGwCViK_0wjQ0CIQDe5Ubu17n0y8Wn8ZmCLguKQlsixk973MXlYZEg4bpwcQ%3D%3D/", "width": 854, "language": null, "vcodec": "avc1.4d4014", "filesize": null, "height": 480, "ext": "mp4"}, {"tbr": 1505.28, "container": "webm_dash", "format_id": "247", "http_headers": {"Accept-Charset": "ISO-8859-1,utf-8;q=0.7,*;q=0.7", "Accept-Language": "en-us,en;q=0.5", "User-Agent": "Mozilla/5.0 (Windows NT 10.0; Win64; x64) AppleWebKit/537.36 (KHTML, like Gecko) Chrome/73.0.3683.112 Safari/537.36", "Accept": "text/html,application/xhtml+xml,application/xml;q=0.9,*/*;q=0.8", "Accept-Encoding": "gzip, deflate"}, "acodec": "none", "format": "247 - 1280x720 (DASH video)", "asr": null, "fragments": [{"path": "sq/0"}, {"duration": 5.339, "path": "sq/1/dur/5.339"}, {"duration": 5.338, "path": "sq/2/dur/5.338"}, {"duration": 5.339, "path": "sq/3/dur/5.339"}, {"duration": 5.339, "path": "sq/4/dur/5.339"}, {"duration": 5.338, "path": "sq/5/dur/5.338"}, {"duration": 5.339, "path": "sq/6/dur/5.339"}, {"duration": 5.339, "path": "sq/7/dur/5.339"}, {"duration": 5.338, "path": "sq/8/dur/5.338"}, {"duration": 5.339, "path": "sq/9/dur/5.339"}, {"duration": 5.339, "path": "sq/10/dur/5.339"}, {"duration": 5.338, "path": "sq/11/dur/5.338"}, {"duration": 5.339, "path": "sq/12/dur/5.339"}, {"duration": 5.339, "path": "sq/13/dur/5.339"}, {"duration": 5.338, "path": "sq/14/dur/5.338"}, {"duration": 5.339, "path": "sq/15/dur/5.339"}, {"duration": 5.339, "path": "sq/16/dur/5.339"}, {"duration": 5.338, "path": "sq/17/dur/5.338"}, {"duration": 5.339, "path": "sq/18/dur/5.339"}, {"duration": 5.339, "path": "sq/19/dur/5.339"}, {"duration": 5.338, "path": "sq/20/dur/5.338"}, {"duration": 5.339, "path": "sq/21/dur/5.339"}, {"duration": 5.339, "path": "sq/22/dur/5.339"}, {"duration": 5.338, "path": "sq/23/dur/5.338"}, {"duration": 5.339, "path": "sq/24/dur/5.339"}, {"duration": 5.339, "path": "sq/25/dur/5.339"}, {"duration": 5.338, "path": "sq/26/dur/5.338"}, {"duration": 5.339, "path": "sq/27/dur/5.339"}, {"duration": 5.339, "path": "sq/28/dur/5.339"}, {"duration": 5.338, "path": "sq/29/dur/5.338"}, {"duration": 5.339, "path": "sq/30/dur/5.339"}, {"duration": 5.339, "path": "sq/31/dur/5.339"}, {"duration": 5.338, "path": "sq/32/dur/5.338"}, {"duration": 5.339, "path": "sq/33/dur/5.339"}, {"duration": 5.339, "path": "sq/34/dur/5.339"}, {"duration": 5.338, "path": "sq/35/dur/5.338"}, {"duration": 5.339, "path": "sq/36/dur/5.339"}, {"duration": 3.871, "path": "sq/37/dur/3.871"}], "manifest_url": "https://manifest.googlevideo.com/api/manifest/dash/expire/1638295021/ei/jRGmYYLMLpOa-gb_uZeYBA/ip/79.129.41.108/id/c66eeb064d77ed9a/source/youtube/requiressl/yes/playback_host/r1---sn-vuxbavcx-5uiee.googlevideo.com/mh/ep/mm/31%2C29/mn/sn-vuxbavcx-5uiee%2Csn-4g5lzner/ms/au%2Crdu/mv/m/mvi/1/pl/20/hfr/all/as/fmp4_audio_clear%2Cwebm_audio_clear%2Cwebm2_audio_clear%2Cfmp4_sd_hd_clear%2Cwebm2_sd_hd_clear/initcwndbps/862500/vprv/1/mt/1638272935/fvip/1/keepalive/yes/fexp/24001373%2C24007246/itag/0/sparams/expire%2Cei%2Cip%2Cid%2Csource%2Crequiressl%2Chfr%2Cas%2Cvprv%2Citag/sig/AOq0QJ8wRQIgBg5L9VNZgI-V1InavELG4dBggS-g10tUMx1DQA9MLhoCIQDnMQDQFjMdXV0sQNk395Y-wTQBU6PwCdQ7ioIy67Hhxg%3D%3D/lsparams/playback_host%2Cmh%2Cmm%2Cmn%2Cms%2Cmv%2Cmvi%2Cpl%2Cinitcwndbps/lsig/AG3C_xAwRQIgbKLa6yYrXhf_Rsup11R-BBJjVSJfUFkqzM62MEGu-rkCIQCg97PRBxRiiLfZrhscwKF7QLpNMFt7R3bo4JUPjGtAXg%3D%3D", "quality": 4, "fps": 30, "protocol": "http_dash_segments", "url": "https://manifest.googlevideo.com/api/manifest/dash/expire/1638295021/ei/jRGmYYLMLpOa-gb_uZeYBA/ip/79.129.41.108/id/c66eeb064d77ed9a/source/youtube/requiressl/yes/playback_host/r1---sn-vuxbavcx-5uiee.googlevideo.com/mh/ep/mm/31%2C29/mn/sn-vuxbavcx-5uiee%2Csn-4g5lzner/ms/au%2Crdu/mv/m/mvi/1/pl/20/hfr/all/as/fmp4_audio_clear%2Cwebm_audio_clear%2Cwebm2_audio_clear%2Cfmp4_sd_hd_clear%2Cwebm2_sd_hd_clear/initcwndbps/862500/vprv/1/mt/1638272935/fvip/1/keepalive/yes/fexp/24001373%2C24007246/itag/0/sparams/expire%2Cei%2Cip%2Cid%2Csource%2Crequiressl%2Chfr%2Cas%2Cvprv%2Citag/sig/AOq0QJ8wRQIgBg5L9VNZgI-V1InavELG4dBggS-g10tUMx1DQA9MLhoCIQDnMQDQFjMdXV0sQNk395Y-wTQBU6PwCdQ7ioIy67Hhxg%3D%3D/lsparams/playback_host%2Cmh%2Cmm%2Cmn%2Cms%2Cmv%2Cmvi%2Cpl%2Cinitcwndbps/lsig/AG3C_xAwRQIgbKLa6yYrXhf_Rsup11R-BBJjVSJfUFkqzM62MEGu-rkCIQCg97PRBxRiiLfZrhscwKF7QLpNMFt7R3bo4JUPjGtAXg%3D%3D", "format_note": "DASH video", "fragment_base_url": "https://r1---sn-vuxbavcx-5uiee.googlevideo.com/videoplayback/expire/1638295021/ei/jRGmYYLMLpOa-gb_uZeYBA/ip/79.129.41.108/id/c66eeb064d77ed9a/itag/247/source/yt_otf/requiressl/yes/mh/ep/mm/31,29/mn/sn-vuxbavcx-5uiee,sn-4g5lzner/ms/au,rdu/mv/m/mvi/1/pl/20/initcwndbps/862500/vprv/1/ratebypass/yes/mime/video%2Fwebm/otfp/1/otf/1/lmt/1602059714097168/mt/1638272935/fvip/1/keepalive/yes/fexp/24001373,24007246/sparams/expire,ei,ip,id,itag,source,requiressl,vprv,ratebypass,mime,otfp,otf,lmt/sig/AOq0QJ8wRgIhALYszNaSQx2qrdTAbGiVVuEbaqI6qYoiFqXjioCIn1i_AiEAx-jEljKjeZ4Qz4nSALhvUI5IQ5wXPgQ4O0rgyEgiD_4%3D/lsparams/mh,mm,mn,ms,mv,mvi,pl,initcwndbps/lsig/AG3C_xAwRQIhALr48BwAfyCYY8BpF4grNnnFfRxlinyx0pCzWKnyAqB6AiB7cwdJ2t6mh3mlz9JX73MZ1S3XHZpYgoRLEKcdU7qqRA%3D%3D/", "width": 1280, "language": null, "vcodec": "vp9", "filesize": null, "height": 720, "ext": "webm"}, {"tbr": 2310.0, "container": "mp4_dash", "format_id": "136", "http_headers": {"Accept-Charset": "ISO-8859-1,utf-8;q=0.7,*;q=0.7", "Accept-Language": "en-us,en;q=0.5", "User-Agent": "Mozilla/5.0 (Windows NT 10.0; Win64; x64) AppleWebKit/537.36 (KHTML, like Gecko) Chrome/73.0.3683.112 Safari/537.36", "Accept": "text/html,application/xhtml+xml,application/xml;q=0.9,*/*;q=0.8", "Accept-Encoding": "gzip, deflate"}, "acodec": "none", "format": "136 - 1280x720 (DASH video)", "asr": null, "fragments": [{"path": "sq/0"}, {"duration": 5.339, "path": "sq/1/dur/5.339"}, {"duration": 5.338, "path": "sq/2/dur/5.338"}, {"duration": 5.339, "path": "sq/3/dur/5.339"}, {"duration": 5.339, "path": "sq/4/dur/5.339"}, {"duration": 5.338, "path": "sq/5/dur/5.338"}, {"duration": 5.339, "path": "sq/6/dur/5.339"}, {"duration": 5.339, "path": "sq/7/dur/5.339"}, {"duration": 5.338, "path": "sq/8/dur/5.338"}, {"duration": 5.339, "path": "sq/9/dur/5.339"}, {"duration": 5.339, "path": "sq/10/dur/5.339"}, {"duration": 5.338, "path": "sq/11/dur/5.338"}, {"duration": 5.339, "path": "sq/12/dur/5.339"}, {"duration": 5.339, "path": "sq/13/dur/5.339"}, {"duration": 5.338, "path": "sq/14/dur/5.338"}, {"duration": 5.339, "path": "sq/15/dur/5.339"}, {"duration": 5.339, "path": "sq/16/dur/5.339"}, {"duration": 5.338, "path": "sq/17/dur/5.338"}, {"duration": 5.339, "path": "sq/18/dur/5.339"}, {"duration": 5.339, "path": "sq/19/dur/5.339"}, {"duration": 5.338, "path": "sq/20/dur/5.338"}, {"duration": 5.339, "path": "sq/21/dur/5.339"}, {"duration": 5.339, "path": "sq/22/dur/5.339"}, {"duration": 5.338, "path": "sq/23/dur/5.338"}, {"duration": 5.339, "path": "sq/24/dur/5.339"}, {"duration": 5.339, "path": "sq/25/dur/5.339"}, {"duration": 5.338, "path": "sq/26/dur/5.338"}, {"duration": 5.339, "path": "sq/27/dur/5.339"}, {"duration": 5.339, "path": "sq/28/dur/5.339"}, {"duration": 5.338, "path": "sq/29/dur/5.338"}, {"duration": 5.339, "path": "sq/30/dur/5.339"}, {"duration": 5.339, "path": "sq/31/dur/5.339"}, {"duration": 5.338, "path": "sq/32/dur/5.338"}, {"duration": 5.339, "path": "sq/33/dur/5.339"}, {"duration": 5.339, "path": "sq/34/dur/5.339"}, {"duration": 5.338, "path": "sq/35/dur/5.338"}, {"duration": 5.339, "path": "sq/36/dur/5.339"}, {"duration": 3.871, "path": "sq/37/dur/3.871"}], "manifest_url": "https://manifest.googlevideo.com/api/manifest/dash/expire/1638295021/ei/jRGmYYLMLpOa-gb_uZeYBA/ip/79.129.41.108/id/c66eeb064d77ed9a/source/youtube/requiressl/yes/playback_host/r1---sn-vuxbavcx-5uiee.googlevideo.com/mh/ep/mm/31%2C29/mn/sn-vuxbavcx-5uiee%2Csn-4g5lzner/ms/au%2Crdu/mv/m/mvi/1/pl/20/hfr/all/as/fmp4_audio_clear%2Cwebm_audio_clear%2Cwebm2_audio_clear%2Cfmp4_sd_hd_clear%2Cwebm2_sd_hd_clear/initcwndbps/862500/vprv/1/mt/1638272935/fvip/1/keepalive/yes/fexp/24001373%2C24007246/itag/0/sparams/expire%2Cei%2Cip%2Cid%2Csource%2Crequiressl%2Chfr%2Cas%2Cvprv%2Citag/sig/AOq0QJ8wRQIgBg5L9VNZgI-V1InavELG4dBggS-g10tUMx1DQA9MLhoCIQDnMQDQFjMdXV0sQNk395Y-wTQBU6PwCdQ7ioIy67Hhxg%3D%3D/lsparams/playback_host%2Cmh%2Cmm%2Cmn%2Cms%2Cmv%2Cmvi%2Cpl%2Cinitcwndbps/lsig/AG3C_xAwRQIgbKLa6yYrXhf_Rsup11R-BBJjVSJfUFkqzM62MEGu-rkCIQCg97PRBxRiiLfZrhscwKF7QLpNMFt7R3bo4JUPjGtAXg%3D%3D", "quality": 4, "fps": 30, "protocol": "http_dash_segments", "url": "https://manifest.googlevideo.com/api/manifest/dash/expire/1638295021/ei/jRGmYYLMLpOa-gb_uZeYBA/ip/79.129.41.108/id/c66eeb064d77ed9a/source/youtube/requiressl/yes/playback_host/r1---sn-vuxbavcx-5uiee.googlevideo.com/mh/ep/mm/31%2C29/mn/sn-vuxbavcx-5uiee%2Csn-4g5lzner/ms/au%2Crdu/mv/m/mvi/1/pl/20/hfr/all/as/fmp4_audio_clear%2Cwebm_audio_clear%2Cwebm2_audio_clear%2Cfmp4_sd_hd_clear%2Cwebm2_sd_hd_clear/initcwndbps/862500/vprv/1/mt/1638272935/fvip/1/keepalive/yes/fexp/24001373%2C24007246/itag/0/sparams/expire%2Cei%2Cip%2Cid%2Csource%2Crequiressl%2Chfr%2Cas%2Cvprv%2Citag/sig/AOq0QJ8wRQIgBg5L9VNZgI-V1InavELG4dBggS-g10tUMx1DQA9MLhoCIQDnMQDQFjMdXV0sQNk395Y-wTQBU6PwCdQ7ioIy67Hhxg%3D%3D/lsparams/playback_host%2Cmh%2Cmm%2Cmn%2Cms%2Cmv%2Cmvi%2Cpl%2Cinitcwndbps/lsig/AG3C_xAwRQIgbKLa6yYrXhf_Rsup11R-BBJjVSJfUFkqzM62MEGu-rkCIQCg97PRBxRiiLfZrhscwKF7QLpNMFt7R3bo4JUPjGtAXg%3D%3D", "format_note": "DASH video", "fragment_base_url": "https://r1---sn-vuxbavcx-5uiee.googlevideo.com/videoplayback/expire/1638295021/ei/jRGmYYLMLpOa-gb_uZeYBA/ip/79.129.41.108/id/c66eeb064d77ed9a/itag/136/source/yt_otf/requiressl/yes/mh/ep/mm/31,29/mn/sn-vuxbavcx-5uiee,sn-4g5lzner/ms/au,rdu/mv/m/mvi/1/pl/20/initcwndbps/862500/vprv/1/ratebypass/yes/mime/video%2Fmp4/otfp/1/otf/1/lmt/1602059714097168/mt/1638272935/fvip/1/keepalive/yes/fexp/24001373,24007246/sparams/expire,ei,ip,id,itag,source,requiressl,vprv,ratebypass,mime,otfp,otf,lmt/sig/AOq0QJ8wRAIgHqVgnKfLc6QlGifoOHwNuCbvcqdnVSqAy36Svqm88K4CICeyUqqW_BWwDHkFtQPAgHuTmBc-BY_qq_oXVmcIB3yn/lsparams/mh,mm,mn,ms,mv,mvi,pl,initcwndbps/lsig/AG3C_xAwRgIhAJ3wXFXZWsQ55eVBk3COssPovcKAFtJOTARa4iSaLg__AiEAnItASRtc_CefjcTJRCs9rf0N4jT71PspoecdgeK1Qro%3D/", "width": 1280, "language": null, "vcodec": "avc1.4d4016", "filesize": null, "height": 720, "ext": "mp4"}, {"tbr": 2646.0, "container": "webm_dash", "format_id": "248", "http_headers": {"Accept-Charset": "ISO-8859-1,utf-8;q=0.7,*;q=0.7", "Accept-Language": "en-us,en;q=0.5", "User-Agent": "Mozilla/5.0 (Windows NT 10.0; Win64; x64) AppleWebKit/537.36 (KHTML, like Gecko) Chrome/73.0.3683.112 Safari/537.36", "Accept": "text/html,application/xhtml+xml,application/xml;q=0.9,*/*;q=0.8", "Accept-Encoding": "gzip, deflate"}, "acodec": "none", "format": "248 - 1920x1080 (DASH video)", "asr": null, "fragments": [{"path": "sq/0"}, {"duration": 5.339, "path": "sq/1/dur/5.339"}, {"duration": 5.338, "path": "sq/2/dur/5.338"}, {"duration": 5.339, "path": "sq/3/dur/5.339"}, {"duration": 5.339, "path": "sq/4/dur/5.339"}, {"duration": 5.338, "path": "sq/5/dur/5.338"}, {"duration": 5.339, "path": "sq/6/dur/5.339"}, {"duration": 5.339, "path": "sq/7/dur/5.339"}, {"duration": 5.338, "path": "sq/8/dur/5.338"}, {"duration": 5.339, "path": "sq/9/dur/5.339"}, {"duration": 5.339, "path": "sq/10/dur/5.339"}, {"duration": 5.338, "path": "sq/11/dur/5.338"}, {"duration": 5.339, "path": "sq/12/dur/5.339"}, {"duration": 5.339, "path": "sq/13/dur/5.339"}, {"duration": 5.338, "path": "sq/14/dur/5.338"}, {"duration": 5.339, "path": "sq/15/dur/5.339"}, {"duration": 5.339, "path": "sq/16/dur/5.339"}, {"duration": 5.338, "path": "sq/17/dur/5.338"}, {"duration": 5.339, "path": "sq/18/dur/5.339"}, {"duration": 5.339, "path": "sq/19/dur/5.339"}, {"duration": 5.338, "path": "sq/20/dur/5.338"}, {"duration": 5.339, "path": "sq/21/dur/5.339"}, {"duration": 5.339, "path": "sq/22/dur/5.339"}, {"duration": 5.338, "path": "sq/23/dur/5.338"}, {"duration": 5.339, "path": "sq/24/dur/5.339"}, {"duration": 5.339, "path": "sq/25/dur/5.339"}, {"duration": 5.338, "path": "sq/26/dur/5.338"}, {"duration": 5.339, "path": "sq/27/dur/5.339"}, {"duration": 5.339, "path": "sq/28/dur/5.339"}, {"duration": 5.338, "path": "sq/29/dur/5.338"}, {"duration": 5.339, "path": "sq/30/dur/5.339"}, {"duration": 5.339, "path": "sq/31/dur/5.339"}, {"duration": 5.338, "path": "sq/32/dur/5.338"}, {"duration": 5.339, "path": "sq/33/dur/5.339"}, {"duration": 5.339, "path": "sq/34/dur/5.339"}, {"duration": 5.338, "path": "sq/35/dur/5.338"}, {"duration": 5.339, "path": "sq/36/dur/5.339"}, {"duration": 3.871, "path": "sq/37/dur/3.871"}], "manifest_url": "https://manifest.googlevideo.com/api/manifest/dash/expire/1638295021/ei/jRGmYYLMLpOa-gb_uZeYBA/ip/79.129.41.108/id/c66eeb064d77ed9a/source/youtube/requiressl/yes/playback_host/r1---sn-vuxbavcx-5uiee.googlevideo.com/mh/ep/mm/31%2C29/mn/sn-vuxbavcx-5uiee%2Csn-4g5lzner/ms/au%2Crdu/mv/m/mvi/1/pl/20/hfr/all/as/fmp4_audio_clear%2Cwebm_audio_clear%2Cwebm2_audio_clear%2Cfmp4_sd_hd_clear%2Cwebm2_sd_hd_clear/initcwndbps/862500/vprv/1/mt/1638272935/fvip/1/keepalive/yes/fexp/24001373%2C24007246/itag/0/sparams/expire%2Cei%2Cip%2Cid%2Csource%2Crequiressl%2Chfr%2Cas%2Cvprv%2Citag/sig/AOq0QJ8wRQIgBg5L9VNZgI-V1InavELG4dBggS-g10tUMx1DQA9MLhoCIQDnMQDQFjMdXV0sQNk395Y-wTQBU6PwCdQ7ioIy67Hhxg%3D%3D/lsparams/playback_host%2Cmh%2Cmm%2Cmn%2Cms%2Cmv%2Cmvi%2Cpl%2Cinitcwndbps/lsig/AG3C_xAwRQIgbKLa6yYrXhf_Rsup11R-BBJjVSJfUFkqzM62MEGu-rkCIQCg97PRBxRiiLfZrhscwKF7QLpNMFt7R3bo4JUPjGtAXg%3D%3D", "quality": 5, "fps": 30, "protocol": "http_dash_segments", "url": "https://manifest.googlevideo.com/api/manifest/dash/expire/1638295021/ei/jRGmYYLMLpOa-gb_uZeYBA/ip/79.129.41.108/id/c66eeb064d77ed9a/source/youtube/requiressl/yes/playback_host/r1---sn-vuxbavcx-5uiee.googlevideo.com/mh/ep/mm/31%2C29/mn/sn-vuxbavcx-5uiee%2Csn-4g5lzner/ms/au%2Crdu/mv/m/mvi/1/pl/20/hfr/all/as/fmp4_audio_clear%2Cwebm_audio_clear%2Cwebm2_audio_clear%2Cfmp4_sd_hd_clear%2Cwebm2_sd_hd_clear/initcwndbps/862500/vprv/1/mt/1638272935/fvip/1/keepalive/yes/fexp/24001373%2C24007246/itag/0/sparams/expire%2Cei%2Cip%2Cid%2Csource%2Crequiressl%2Chfr%2Cas%2Cvprv%2Citag/sig/AOq0QJ8wRQIgBg5L9VNZgI-V1InavELG4dBggS-g10tUMx1DQA9MLhoCIQDnMQDQFjMdXV0sQNk395Y-wTQBU6PwCdQ7ioIy67Hhxg%3D%3D/lsparams/playback_host%2Cmh%2Cmm%2Cmn%2Cms%2Cmv%2Cmvi%2Cpl%2Cinitcwndbps/lsig/AG3C_xAwRQIgbKLa6yYrXhf_Rsup11R-BBJjVSJfUFkqzM62MEGu-rkCIQCg97PRBxRiiLfZrhscwKF7QLpNMFt7R3bo4JUPjGtAXg%3D%3D", "format_note": "DASH video", "fragment_base_url": "https://r1---sn-vuxbavcx-5uiee.googlevideo.com/videoplayback/expire/1638295021/ei/jRGmYYLMLpOa-gb_uZeYBA/ip/79.129.41.108/id/c66eeb064d77ed9a/itag/248/source/yt_otf/requiressl/yes/mh/ep/mm/31,29/mn/sn-vuxbavcx-5uiee,sn-4g5lzner/ms/au,rdu/mv/m/mvi/1/pl/20/initcwndbps/862500/vprv/1/ratebypass/yes/mime/video%2Fwebm/otfp/1/otf/1/lmt/1602059714097168/mt/1638272935/fvip/1/keepalive/yes/fexp/24001373,24007246/sparams/expire,ei,ip,id,itag,source,requiressl,vprv,ratebypass,mime,otfp,otf,lmt/sig/AOq0QJ8wRQIhAO_IU_XmqURMw3h7fTX53gxTKR942GuJqbUo6VHCduj8AiBHxHtU1FkH9U-R4Nhb4C-uJf3U3_uj3HTI3IUP1zUMng%3D%3D/lsparams/mh,mm,mn,ms,mv,mvi,pl,initcwndbps/lsig/AG3C_xAwRgIhAI0xImE_JYaczi92VEcOaVvG0iHYw6kw1rqO8-Ir_ehzAiEA_uB8GyrubL12OiWtl3LPZreoNvfKPDWnLNdHjsuRrg0%3D/", "width": 1920, "language": null, "vcodec": "vp9", "filesize": null, "height": 1080, "ext": "webm"}, {"tbr": 4331.25, "container": "mp4_dash", "format_id": "137", "http_headers": {"Accept-Charset": "ISO-8859-1,utf-8;q=0.7,*;q=0.7", "Accept-Language": "en-us,en;q=0.5", "User-Agent": "Mozilla/5.0 (Windows NT 10.0; Win64; x64) AppleWebKit/537.36 (KHTML, like Gecko) Chrome/73.0.3683.112 Safari/537.36", "Accept": "text/html,application/xhtml+xml,application/xml;q=0.9,*/*;q=0.8", "Accept-Encoding": "gzip, deflate"}, "acodec": "none", "format": "137 - 1920x1080 (DASH video)", "asr": null, "fragments": [{"path": "sq/0"}, {"duration": 5.339, "path": "sq/1/dur/5.339"}, {"duration": 5.338, "path": "sq/2/dur/5.338"}, {"duration": 5.339, "path": "sq/3/dur/5.339"}, {"duration": 5.339, "path": "sq/4/dur/5.339"}, {"duration": 5.338, "path": "sq/5/dur/5.338"}, {"duration": 5.339, "path": "sq/6/dur/5.339"}, {"duration": 5.339, "path": "sq/7/dur/5.339"}, {"duration": 5.338, "path": "sq/8/dur/5.338"}, {"duration": 5.339, "path": "sq/9/dur/5.339"}, {"duration": 5.339, "path": "sq/10/dur/5.339"}, {"duration": 5.338, "path": "sq/11/dur/5.338"}, {"duration": 5.339, "path": "sq/12/dur/5.339"}, {"duration": 5.339, "path": "sq/13/dur/5.339"}, {"duration": 5.338, "path": "sq/14/dur/5.338"}, {"duration": 5.339, "path": "sq/15/dur/5.339"}, {"duration": 5.339, "path": "sq/16/dur/5.339"}, {"duration": 5.338, "path": "sq/17/dur/5.338"}, {"duration": 5.339, "path": "sq/18/dur/5.339"}, {"duration": 5.339, "path": "sq/19/dur/5.339"}, {"duration": 5.338, "path": "sq/20/dur/5.338"}, {"duration": 5.339, "path": "sq/21/dur/5.339"}, {"duration": 5.339, "path": "sq/22/dur/5.339"}, {"duration": 5.338, "path": "sq/23/dur/5.338"}, {"duration": 5.339, "path": "sq/24/dur/5.339"}, {"duration": 5.339, "path": "sq/25/dur/5.339"}, {"duration": 5.338, "path": "sq/26/dur/5.338"}, {"duration": 5.339, "path": "sq/27/dur/5.339"}, {"duration": 5.339, "path": "sq/28/dur/5.339"}, {"duration": 5.338, "path": "sq/29/dur/5.338"}, {"duration": 5.339, "path": "sq/30/dur/5.339"}, {"duration": 5.339, "path": "sq/31/dur/5.339"}, {"duration": 5.338, "path": "sq/32/dur/5.338"}, {"duration": 5.339, "path": "sq/33/dur/5.339"}, {"duration": 5.339, "path": "sq/34/dur/5.339"}, {"duration": 5.338, "path": "sq/35/dur/5.338"}, {"duration": 5.339, "path": "sq/36/dur/5.339"}, {"duration": 3.871, "path": "sq/37/dur/3.871"}], "manifest_url": "https://manifest.googlevideo.com/api/manifest/dash/expire/1638295021/ei/jRGmYYLMLpOa-gb_uZeYBA/ip/79.129.41.108/id/c66eeb064d77ed9a/source/youtube/requiressl/yes/playback_host/r1---sn-vuxbavcx-5uiee.googlevideo.com/mh/ep/mm/31%2C29/mn/sn-vuxbavcx-5uiee%2Csn-4g5lzner/ms/au%2Crdu/mv/m/mvi/1/pl/20/hfr/all/as/fmp4_audio_clear%2Cwebm_audio_clear%2Cwebm2_audio_clear%2Cfmp4_sd_hd_clear%2Cwebm2_sd_hd_clear/initcwndbps/862500/vprv/1/mt/1638272935/fvip/1/keepalive/yes/fexp/24001373%2C24007246/itag/0/sparams/expire%2Cei%2Cip%2Cid%2Csource%2Crequiressl%2Chfr%2Cas%2Cvprv%2Citag/sig/AOq0QJ8wRQIgBg5L9VNZgI-V1InavELG4dBggS-g10tUMx1DQA9MLhoCIQDnMQDQFjMdXV0sQNk395Y-wTQBU6PwCdQ7ioIy67Hhxg%3D%3D/lsparams/playback_host%2Cmh%2Cmm%2Cmn%2Cms%2Cmv%2Cmvi%2Cpl%2Cinitcwndbps/lsig/AG3C_xAwRQIgbKLa6yYrXhf_Rsup11R-BBJjVSJfUFkqzM62MEGu-rkCIQCg97PRBxRiiLfZrhscwKF7QLpNMFt7R3bo4JUPjGtAXg%3D%3D", "quality": 5, "fps": 30, "protocol": "http_dash_segments", "url": "https://manifest.googlevideo.com/api/manifest/dash/expire/1638295021/ei/jRGmYYLMLpOa-gb_uZeYBA/ip/79.129.41.108/id/c66eeb064d77ed9a/source/youtube/requiressl/yes/playback_host/r1---sn-vuxbavcx-5uiee.googlevideo.com/mh/ep/mm/31%2C29/mn/sn-vuxbavcx-5uiee%2Csn-4g5lzner/ms/au%2Crdu/mv/m/mvi/1/pl/20/hfr/all/as/fmp4_audio_clear%2Cwebm_audio_clear%2Cwebm2_audio_clear%2Cfmp4_sd_hd_clear%2Cwebm2_sd_hd_clear/initcwndbps/862500/vprv/1/mt/1638272935/fvip/1/keepalive/yes/fexp/24001373%2C24007246/itag/0/sparams/expire%2Cei%2Cip%2Cid%2Csource%2Crequiressl%2Chfr%2Cas%2Cvprv%2Citag/sig/AOq0QJ8wRQIgBg5L9VNZgI-V1InavELG4dBggS-g10tUMx1DQA9MLhoCIQDnMQDQFjMdXV0sQNk395Y-wTQBU6PwCdQ7ioIy67Hhxg%3D%3D/lsparams/playback_host%2Cmh%2Cmm%2Cmn%2Cms%2Cmv%2Cmvi%2Cpl%2Cinitcwndbps/lsig/AG3C_xAwRQIgbKLa6yYrXhf_Rsup11R-BBJjVSJfUFkqzM62MEGu-rkCIQCg97PRBxRiiLfZrhscwKF7QLpNMFt7R3bo4JUPjGtAXg%3D%3D", "format_note": "DASH video", "fragment_base_url": "https://r1---sn-vuxbavcx-5uiee.googlevideo.com/videoplayback/expire/1638295021/ei/jRGmYYLMLpOa-gb_uZeYBA/ip/79.129.41.108/id/c66eeb064d77ed9a/itag/137/source/yt_otf/requiressl/yes/mh/ep/mm/31,29/mn/sn-vuxbavcx-5uiee,sn-4g5lzner/ms/au,rdu/mv/m/mvi/1/pl/20/initcwndbps/862500/vprv/1/ratebypass/yes/mime/video%2Fmp4/otfp/1/otf/1/lmt/1602059714097168/mt/1638272935/fvip/1/keepalive/yes/fexp/24001373,24007246/sparams/expire,ei,ip,id,itag,source,requiressl,vprv,ratebypass,mime,otfp,otf,lmt/sig/AOq0QJ8wRQIhAK8bQW0YI2S_j6rwDsarXu8UfYre7bCUhGYQJ3HX1SjZAiAwm_sqXyQF9Vjrwz4EClLYJ18laUDnF9L9dPc6eVIDWg%3D%3D/lsparams/mh,mm,mn,ms,mv,mvi,pl,initcwndbps/lsig/AG3C_xAwRQIgH8gGGaSEvL8ed3cZA7eMRGQAlqz9Ruyfy2Ky9_VzD1YCIQDuX68D2NS0N5IFqWAhwCGrDa1Jf_N0NnKLzWeAdk6duQ%3D%3D/", "width": 1920, "language": null, "vcodec": "avc1.64001e", "filesize": null, "height": 1080, "ext": "mp4"}, {"tbr": 564.34, "format": "18 - 640x360 (360p)", "format_id": "18", "acodec": "mp4a.40.2", "http_headers": {"Accept-Charset": "ISO-8859-1,utf-8;q=0.7,*;q=0.7", "Accept-Language": "en-us,en;q=0.5", "User-Agent": "Mozilla/5.0 (Windows NT 10.0; Win64; x64) AppleWebKit/537.36 (KHTML, like Gecko) Chrome/73.0.3683.112 Safari/537.36", "Accept": "text/html,application/xhtml+xml,application/xml;q=0.9,*/*;q=0.8", "Accept-Encoding": "gzip, deflate"}, "asr": 44100, "quality": 2, "fps": 30, "protocol": "https", "url": "https://r1---sn-vuxbavcx-5uiee.googlevideo.com/videoplayback?expire=1638295021&ei=jRGmYYLMLpOa-gb_uZeYBA&ip=79.129.41.108&id=o-ALrcOYgiOnLo48mGoquBYgezOis_kAvQ_cLt-BIQZolS&itag=18&source=youtube&requiressl=yes&mh=ep&mm=31%2C29&mn=sn-vuxbavcx-5uiee%2Csn-4g5lzner&ms=au%2Crdu&mv=m&mvi=1&pl=20&initcwndbps=862500&vprv=1&mime=video%2Fmp4&ns=Vmz5K8CVriyIFOg1EKWLHhIG&gir=yes&clen=13834458&ratebypass=yes&dur=196.115&lmt=1528053176088895&mt=1638272935&fvip=1&fexp=24001373%2C24007246&c=WEB&n=VH-nmPrw-bBC8A2v&sparams=expire%2Cei%2Cip%2Cid%2Citag%2Csource%2Crequiressl%2Cvprv%2Cmime%2Cns%2Cgir%2Cclen%2Cratebypass%2Cdur%2Clmt&sig=AOq0QJ8wRQIhAO9GGMIENMibDLWf6LV1oZVyqEKKhCUQm_SIyCMKRWvrAiAqWbAVcweZnbWl8V9ukswGk-zyJVfJN-ffcobLrMKi8Q%3D%3D&lsparams=mh%2Cmm%2Cmn%2Cms%2Cmv%2Cmvi%2Cpl%2Cinitcwndbps&lsig=AG3C_xAwRQIgSwq_KAypJVpqeKGTqprQo0e0dw80SS4Jd7Jp0ykmxEsCIQD7L18OwAhQUzTkpcSoaj5PRVDrPiPG6pzp39zeQ6VZgw%3D%3D", "format_note": "360p", "filesize": 13834458, "vcodec": "avc1.42001E", "width": 640, "height": 360, "ext": "mp4"}, {"tbr": 2139.091, "format": "22 - 1280x720 (720p)", "format_id": "22", "acodec": "mp4a.40.2", "http_headers": {"Accept-Charset": "ISO-8859-1,utf-8;q=0.7,*;q=0.7", "Accept-Language": "en-us,en;q=0.5", "User-Agent": "Mozilla/5.0 (Windows NT 10.0; Win64; x64) AppleWebKit/537.36 (KHTML, like Gecko) Chrome/73.0.3683.112 Safari/537.36", "Accept": "text/html,application/xhtml+xml,application/xml;q=0.9,*/*;q=0.8", "Accept-Encoding": "gzip, deflate"}, "asr": 44100, "quality": 4, "fps": 30, "protocol": "https", "url": "https://r1---sn-vuxbavcx-5uiee.googlevideo.com/videoplayback?expire=1638295021&ei=jRGmYYLMLpOa-gb_uZeYBA&ip=79.129.41.108&id=o-ALrcOYgiOnLo48mGoquBYgezOis_kAvQ_cLt-BIQZolS&itag=22&source=youtube&requiressl=yes&mh=ep&mm=31%2C29&mn=sn-vuxbavcx-5uiee%2Csn-4g5lzner&ms=au%2Crdu&mv=m&mvi=1&pl=20&initcwndbps=862500&vprv=1&mime=video%2Fmp4&ns=Vmz5K8CVriyIFOg1EKWLHhIG&ratebypass=yes&dur=196.115&lmt=1528053287177039&mt=1638272935&fvip=1&fexp=24001373%2C24007246&c=WEB&n=VH-nmPrw-bBC8A2v&sparams=expire%2Cei%2Cip%2Cid%2Citag%2Csource%2Crequiressl%2Cvprv%2Cmime%2Cns%2Cratebypass%2Cdur%2Clmt&sig=AOq0QJ8wRQIhAOv_ysamTe-4ajo8v8ThvNJaOGTCth5tCIWat4agPS4hAiBoppHyjvv-OMsbVLEE7slvf5PbFDBgut3cyfNGuKZcWg%3D%3D&lsparams=mh%2Cmm%2Cmn%2Cms%2Cmv%2Cmvi%2Cpl%2Cinitcwndbps&lsig=AG3C_xAwRQIgSwq_KAypJVpqeKGTqprQo0e0dw80SS4Jd7Jp0ykmxEsCIQD7L18OwAhQUzTkpcSoaj5PRVDrPiPG6pzp39zeQ6VZgw%3D%3D", "format_note": "720p", "filesize": null, "vcodec": "avc1.64001F", "width": 1280, "height": 720, "ext": "mp4"}], "thumbnails": [{"id": "0", "width": 168, "resolution": "168x94", "height": 94, "url": "https://i.ytimg.com/vi/xm7rBk137Zo/hqdefault.jpg?sqp=-oaymwEbCKgBEF5IVfKriqkDDggBFQAAiEIYAXABwAEG&rs=AOn4CLDsvChOb5FrAlaJ04C6n8ji7wKZjw"}, {"id": "1", "width": 196, "resolution": "196x110", "height": 110, "url": "https://i.ytimg.com/vi/xm7rBk137Zo/hqdefault.jpg?sqp=-oaymwEbCMQBEG5IVfKriqkDDggBFQAAiEIYAXABwAEG&rs=AOn4CLAhJfEVImds3vGMkd0HkWNezogJRw"}, {"id": "2", "width": 246, "resolution": "246x138", "height": 138, "url": "https://i.ytimg.com/vi/xm7rBk137Zo/hqdefault.jpg?sqp=-oaymwEcCPYBEIoBSFXyq4qpAw4IARUAAIhCGAFwAcABBg==&rs=AOn4CLA6KSnCONlFkLJCoAI0pepTZKiACQ"}, {"id": "3", "width": 336, "resolution": "336x188", "height": 188, "url": "https://i.ytimg.com/vi/xm7rBk137Zo/hqdefault.jpg?sqp=-oaymwEcCNACELwBSFXyq4qpAw4IARUAAIhCGAFwAcABBg==&rs=AOn4CLA2h-EOb1PAQmHhYyC0TIFMz97Dmw"}], "view_count": 841, "format_note": "720p", "average_rating": 5.0, "playlist_index": null, "_filename": "xm7rBk137Zo.mp4", "description": "Michael Stephens' Bending Reality TV - http://BendingRealityTV.com\n\nIn this interview Michael Stephens catches up with legendary musician George Benson. You may know George by some his songs such as In Your Eyes, Love X Love, Lady Love Me, Greatest Love of All, Love Ballad, Inside Love, On Broadway, This Masquerade, Turn Your Love Around, Give Me The Night. George discusses his charity performance, traveling, Andrea Bocelli, Robin Thicke, his Nat King Cole project and more.\n\nAbout Bending Reality TV\u2122\nIs it possible to change your reality and The Matrix by becoming more aware, getting energized and taking responsibility for you desires? Yes. Bending Reality TV\u2122 follows Intuitive Businessman, Name Reader\u2122, and Remote Influencer Michael Stephens as he changes lives and explores the world. You can learn more about Bending Reality TV and the work of Michael Stephens at: http://www.BendingRealityTV.com\n\nCopyright \u00a92009-2018 Michael Stephens and Bending Reality Productions. All Rights Reserved.", "ext": "mp4", "channel_id": "UC2vfkujTcRr2bU0jThVMu_A", "channel": "Bending Reality TV", "acodec": "mp4a.40.2", "channel_url": "https://www.youtube.com/channel/UC2vfkujTcRr2bU0jThVMu_A", "uploader": "Bending Reality TV", "filesize": null, "uploader_url": "http://www.youtube.com/user/BendingRealityTV", "vcodec": "avc1.64001F", "display_id": "xm7rBk137Zo", "tbr": 2139.091, "http_headers": {"Accept-Charset": "ISO-8859-1,utf-8;q=0.7,*;q=0.7", "Accept-Language": "en-us,en;q=0.5", "User-Agent": "Mozilla/5.0 (Windows NT 10.0; Win64; x64) AppleWebKit/537.36 (KHTML, like Gecko) Chrome/73.0.3683.112 Safari/537.36", "Accept": "text/html,application/xhtml+xml,application/xml;q=0.9,*/*;q=0.8", "Accept-Encoding": "gzip, deflate"}, "duration": 196, "webpage_url_basename": "watch", "fulltitle": "Michael Stephens Interview with Legendary Musician George Benson", "upload_date": "20180603", "playlist": null, "width": 1280, "uploader_id": "BendingRealityTV", "protocol": "https", "thumbnail": "https://i.ytimg.com/vi/xm7rBk137Zo/hqdefault.jpg?sqp=-oaymwEcCNACELwBSFXyq4qpAw4IARUAAIhCGAFwAcABBg==&rs=AOn4CLA2h-EOb1PAQmHhYyC0TIFMz97Dmw", "format_id": "22", "title": "Michael Stephens Interview with Legendary Musician George Benson", "tags": ["Michael Stephens", "Bending Reality TV", "Reality TV", "Las Vegas", "Self Healing Group", "Name Reading", "The Push", "Psychic Energy Reader", "The Meeting", "Psychic", "Remote Influencing", "Life Coach", "Illuminati", "George Benson", "George Benson Music", "Andrea Bocelli", "Power of Love Gala", "Keep Memory Alive", "KeepMemoryAlive", "MGM Grand", "Andrea Bocelli Foundation", "Opera", "Red Carpet", "Charity", "Cleveland Clinic", "Brain Health"], "id": "xm7rBk137Zo", "quality": 4, "age_limit": 0, "categories": ["Music"], "url": "https://r1---sn-vuxbavcx-5uiee.googlevideo.com/videoplayback?expire=1638295021&ei=jRGmYYLMLpOa-gb_uZeYBA&ip=79.129.41.108&id=o-ALrcOYgiOnLo48mGoquBYgezOis_kAvQ_cLt-BIQZolS&itag=22&source=youtube&requiressl=yes&mh=ep&mm=31%2C29&mn=sn-vuxbavcx-5uiee%2Csn-4g5lzner&ms=au%2Crdu&mv=m&mvi=1&pl=20&initcwndbps=862500&vprv=1&mime=video%2Fmp4&ns=Vmz5K8CVriyIFOg1EKWLHhIG&ratebypass=yes&dur=196.115&lmt=1528053287177039&mt=1638272935&fvip=1&fexp=24001373%2C24007246&c=WEB&n=VH-nmPrw-bBC8A2v&sparams=expire%2Cei%2Cip%2Cid%2Citag%2Csource%2Crequiressl%2Cvprv%2Cmime%2Cns%2Cratebypass%2Cdur%2Clmt&sig=AOq0QJ8wRQIhAOv_ysamTe-4ajo8v8ThvNJaOGTCth5tCIWat4agPS4hAiBoppHyjvv-OMsbVLEE7slvf5PbFDBgut3cyfNGuKZcWg%3D%3D&lsparams=mh%2Cmm%2Cmn%2Cms%2Cmv%2Cmvi%2Cpl%2Cinitcwndbps&lsig=AG3C_xAwRQIgSwq_KAypJVpqeKGTqprQo0e0dw80SS4Jd7Jp0ykmxEsCIQD7L18OwAhQUzTkpcSoaj5PRVDrPiPG6pzp39zeQ6VZgw%3D%3D", "extractor_key": "Youtube", "fps": 30, "height": 720}